Workbook

Sheet Resumen General
B3: MIMPARA, NPLATE, ARANESP, VECTIBIX, PROLIA,REPATHA,BLINCYTO & XGEVA
B4: RESUMEN GENERAL
B5: DEL 01 AL 31 DE MAYO 2018
C9: Valores
B10: Presentación | C10: PZAS MES ACT | D10: % PART
B11: ARANESP 300MCG/0.6ML JPRELL CAJ C/1 | C11: 89 | D11: 0.022704082
B12: ARANESP 30MCG/0.3ML JPRELL CAJ C/4 | C12: 14 | D12: 0.0035714286
B13: ARANESP 40MCG/0.4ML JPRELL CAJ C/4 | C13: 53 | D13: 0.013520408
B14: ARANESP 500MCG/1ML JPRELL CAJ C/1 | C14: 98 | D14: 0.025
B15: ARANESP 60MCG/0.3ML JPRELL CAJ C/4 | C15: 77 | D15: 0.019642857
B16: ARANESP 80MCG/0.4ML JGP CAJ C/1 | C16: 87 | D16: 0.022193878
B17: BLINCYTO 35MCG FAM CAJ C/1 | C17: 20 | D17: 0.0051020408
B18: KYPROLIS 60MG FAM CAJ C/1 | C18: 47 | D18: 0.011989796
B19: MIMPARA 30MG TAB CAJ C/30 | C19: 133 | D19: 0.033928571
B20: NEULASTIM 6 mg/0.6 ml JGP CAJ C/1 | C20: 159 | D20: 0.040561224
B21: NEUPOGEN 300 mcg/0.5 ml 1 JGP C/0.5 ml | C21: 727 | D21: 0.18545918
B22: NPLATE 250 mcg FAM C/1 | C22: 171 | D22: 0.043622449
... B27: Total general | C27: 3920 | D27: 1

Sheet Acumulado Anual
B2: MIMPARA, NPLATE, ARANESP, VECTIBIX, PROLIA,REPATHA,BLINCYTO & XGEVA
B3: ACUMULADO ANUAL
B4: ='Resumen General'!B5 -> DEL 01 AL 31 DE MAYO 2018
B7: FAMILIA | C7: 40544 | D7: 40575 | E7: 40603 | F7: 40634 | G7: 40664 | H7: 40695 | I7: 40725 | J7: 40756 | K7: 40787 | L7: 40817 | M7: 40848 | N7: 40878 | O7: Total 2011 | P7: 40909 | Q7: 40940 | R7: 40969 | S7: 41000 | T7: 41030 | U7: 41061 | V7: 41091 | W7: 41122 | X7: 41153 | Y7: 41183 | Z7: 41214 | AA7: 41244 | AB7: Total 2012 | AC7: 41275 | AD7: 41306 | AE7: 41334 | AF7: 41365 | AG7: 41395 | AH7: 41426 | AI7: 41456 | AJ7: 41487 | AK7: 41518 | AL7: 41548 | AM7: 41579 | AN7: 41609 | AO7: Total 2013 | AP7: 41640 | AQ7: 41671 | AR7: 41699 | AS7: 41730 | AT7: 41760 | AU7: 41791 | AV7: 41821 | AW7: 41852 | AX7: 41883 | AY7: 41913 | AZ7: 41944 | BA7: 41974 | BB7: Total 2014 | BC7: 42005 | BD7: 42036 | BE7: 42064 | BF7: 42095 | BG7: 42125 | BH7: 42156 | BI7: 42186 | BJ7: 42217 | BK7: 42248 | BL7: 42278 | BM7: 42309 | BN7: 42339 | BO7: Total 2015 | BP7: 42370 | BQ7: 42401 | BR7: 42430 | BS7: 42461 | BT7: 42491 | BU7: 42522 | BV7: 42552 | BW7: 42583 | BX7: 42614 | BY7: 42644 | BZ7: 42675 | CA7: 42705 | CB7: Total 2016 | CC7: 42736 | CD7: 42767 | CE7: 42798 | CF7: 42829 | CG7: 42860 | CH7: 42891 | CI7: 42922 | CJ7: 42953 | CK7: 42984 | CL7: 43015 | CM7: 43046 | CN7: 43077 | CO7: Total 2017 | CP7: 43101 | CQ7: 43132 | CR7: 43163 | CS7: 43194 | CT7: 43225 | CU7: 43256 | CV7: 43287 | CW7: 43318 | CX7: 43349 | CY7: 43380 | CZ7: 43411 | DA7: 43442 | DB7: Total 2018 | DD7: Total General
B8: NEUPOGEN | C8: 0 | D8: 0 | E8: 0 | F8: 0 | G8: 0 | H8: 0 | I8: 0 | J8: 0 | K8: 0 | L8: 0 | M8: 0 | N8: 0 | O8: =+SUM(C8:N8) -> 0 | P8: 0 | Q8: 0 | R8: 0 | S8: 0 | T8: 0 | U8: 0 | V8: 0 | W8: 0 | X8: 0 | Y8: 0 | Z8: 0 | AA8: 0 | AB8: =SUM($P8:$AA8) -> 0 | AC8: 1032 | AD8: 750 | AE8: 1087 | AF8: 1247 | AG8: 1045 | AH8: 1124 | AI8: 1454 | AJ8: 1071 | AK8: 1065 | AL8: 1264 | AM8: 824 | AN8: 721 | AO8: =SUM(AC8:AN8) -> 12684 | AP8: 729 | AQ8: 808 | AR8: 710 | AS8: 895 | AT8: 1077 | AU8: 968 | AV8: 1136 | AW8: 1003 | AX8: 692 | AY8: 903 | AZ8: 1217 | BA8: 1283 | BB8: =SUM(AP8:BA8) -> 11421 | BC8: 1023 | BD8: 874 | BE8: 1045 | BF8: 1090 | BG8: 951 | BH8: 1140 | BI8: 1199 | BJ8: 928 | BK8: 1257 | BL8: 1301 | BM8: 1098 | BN8: 1142 | BO8: =SUM(BC8:BN8) -> 13048 | BP8: 982 | BQ8: 1057 | BR8: 1063 | BS8: 738 | BT8: 665 | BU8: 1011 | BV8: 1015 | BW8: 1171 | BX8: 1104 | BY8: 1039 | BZ8: 1088 | CA8: 1075 | CB8: =SUM(BP8:CA8) -> 12008 | CC8: 975 | CD8: 696 | CE8: 850 | CF8: 648 | CG8: 1009 | CH8: 734 | CI8: 797 | CJ8: 860 | CK8: 805 | CL8: 788 | CM8: 793 | CN8: 612 | CO8: =SUM(CC8:CN8) -> 9567 | CP8: 620 | CQ8: 602 | CR8: 687 | CS8: 558 | CT8: 727 | DB8: =SUM(CP8:DA8) -> 3194 | DD8: =SUM(O8+AB8+AO8+BB8+BO8+CB8+CO8+DB8) -> 61922
B9: PROLIA | C9: 0 | D9: 0 | E9: 0 | F9: 0 | G9: 0 | H9: 0 | I9: 0 | J9: 0 | K9: 0 | L9: 0 | M9: 0 | N9: 0 | O9: =+SUM(C9:N9) -> 0 | P9: 0 | Q9: 25 | R9: 75 | S9: 80 | T9: 127 | U9: 164 | V9: 204 | W9: 211 | X9: 211 | Y9: 271 | Z9: 314 | AA9: 317 | AB9: =SUM($P9:$AA9) -> 1999 | AC9: 356 | AD9: 354 | AE9: 404 | AF9: 471 | AG9: 539 | AH9: 536 | AI9: 517 | AJ9: 531 | AK9: 576 | AL9: 632 | AM9: 690 | AN9: 691 | AO9: =SUM(AC9:AN9) -> 6297 | AP9: 834 | AQ9: 741 | AR9: 911 | AS9: 869 | AT9: 946 | AU9: 857 | AV9: 979 | AW9: 925 | AX9: 971 | AY9: 995 | AZ9: 951 | BA9: 1017 | BB9: =SUM(AP9:BA9) -> 10996 | BC9: 985 | BD9: 989 | BE9: 1186 | BF9: 1050 | BG9: 1060 | BH9: 1142 | BI9: 1186 | BJ9: 1100 | BK9: 1164 | BL9: 1315 | BM9: 1146 | BN9: 1193 | BO9: =SUM(BC9:BN9) -> 13516 | BP9: 1207 | BQ9: 1254 | BR9: 1349 | BS9: 1416 | BT9: 1369 | BU9: 1450 | BV9: 1371 | BW9: 1408 | BX9: 1270 | BY9: 1408 | BZ9: 1310 | CA9: 1337 | CB9: =SUM(BP9:CA9) -> 16149 | CC9: 1310 | CD9: 1328 | CE9: 1387 | CF9: 1153 | CG9: 1289 | CH9: 1319 | CI9: 1232 | CJ9: 1340 | CK9: 1178 | CL9: 1203 | CM9: 1296 | CN9: 1284 | CO9: =SUM(CC9:CN9) -> 15319 | CP9: 1266 | CQ9: 1148 | CR9: 1274 | CS9: 1320 | CT9: 1483 | DB9: =SUM(CP9:DA9) -> 6491 | DD9: =SUM(O9+AB9+AO9+BB9+BO9+CB9+CO9+DB9) -> 70767
B10: ARANESP | C10: 0 | D10: 0 | E10: 0 | F10: 0 | G10: 0 | H10: 0 | I10: 0 | J10: 0 | K10: 28 | L10: 68 | M10: 64 | N10: 101 | O10: =+SUM(C10:N10) -> 261 | P10: 95 | Q10: 113 | R10: 110 | S10: 139 | T10: 115 | U10: 135 | V10: 174 | W10: 220 | X10: 214 | Y10: 265 | Z10: 246 | AA10: 202 | AB10: =SUM($P10:$AA10) -> 2028 | AC10: 283 | AD10: 254 | AE10: 261 | AF10: 287 | AG10: 272 | AH10: 280 | AI10: 315 | AJ10: 354 | AK10: 299 | AL10: 450 | AM10: 346 | AN10: 317 | AO10: =SUM(AC10:AN10) -> 3718 | AP10: 379 | AQ10: 311 | AR10: 364 | AS10: 336 | AT10: 395 | AU10: 360 | AV10: 376 | AW10: 418 | AX10: 261 | AY10: 268 | AZ10: 260 | BA10: 260 | BB10: =SUM(AP10:BA10) -> 3988 | BC10: 247 | BD10: 269 | BE10: 307 | BF10: 265 | BG10: 291 | BH10: 319 | BI10: 364 | BJ10: 290 | BK10: 327 | BL10: 412 | BM10: 321 | BN10: 291 | BO10: =SUM(BC10:BN10) -> 3703 | BP10: 318 | BQ10: 312 | BR10: 348 | BS10: 342 | BT10: 334 | BU10: 373 | BV10: 399 | BW10: 397 | BX10: 343 | BY10: 365 | BZ10: 330 | CA10: 327 | CB10: =SUM(BP10:CA10) -> 4188 | CC10: 334 | CD10: 277 | CE10: 352 | CF10: 319 | CG10: 370 | CH10: 341 | CI10: 338 | CJ10: 358 | CK10: 344 | CL10: 338 | CM10: 304 | CN10: 315 | CO10: =SUM(CC10:CN10) -> 3990 | CP10: 381 | CQ10: 339 | CR10: 366 | CS10: 368 | CT10: 418 | DB10: =SUM(CP10:DA10) -> 1872 | DD10: =SUM(O10+AB10+AO10+BB10+BO10+CB10+CO10+DB10) -> 23748
B11: NPLATE | C11: 0 | D11: 6 | E11: 5 | F11: 9 | G11: 33 | H11: 44 | I11: 55 | J11: 58 | K11: 54 | L11: 83 | M11: 49 | N11: 62 | O11: =+SUM(C11:N11) -> 458 | P11: 52 | Q11: 73 | R11: 84 | S11: 81 | T11: 102 | U11: 92 | V11: 123 | W11: 182 | X11: 161 | Y11: 136 | Z11: 162 | AA11: 144 | AB11: =SUM($P11:$AA11) -> 1392 | AC11: 167 | AD11: 149 | AE11: 146 | AF11: 172 | AG11: 221 | AH11: 169 | AI11: 190 | AJ11: 230 | AK11: 177 | AL11: 213 | AM11: 213 | AN11: 219 | AO11: =SUM(AC11:AN11) -> 2266 | AP11: 215 | AQ11: 231 | AR11: 259 | AS11: 245 | AT11: 206 | AU11: 177 | AV11: 187 | AW11: 222 | AX11: 173 | AY11: 149 | AZ11: 130 | BA11: 158 | BB11: =SUM(AP11:BA11) -> 2352 | BC11: 199 | BD11: 136 | BE11: 145 | BF11: 140 | BG11: 169 | BH11: 166 | BI11: 136 | BJ11: 125 | BK11: 176 | BL11: 183 | BM11: 154 | BN11: 183 | BO11: =SUM(BC11:BN11) -> 1912 | BP11: 162 | BQ11: 132 | BR11: 163 | BS11: 148 | BT11: 156 | BU11: 147 | BV11: 154 | BW11: 102 | BX11: 143 | BY11: 146 | BZ11: 138 | CA11: 113 | CB11: =SUM(BP11:CA11) -> 1704 | CC11: 132 | CD11: 149 | CE11: 139 | CF11: 133 | CG11: 144 | CH11: 139 | CI11: 145 | CJ11: 122 | CK11: 167 | CL11: 227 | CM11: 181 | CN11: 205 | CO11: =SUM(CC11:CN11) -> 1883 | CP11: 171 | CQ11: 184 | CR11: 182 | CS11: 177 | CT11: 171 | DB11: =SUM(CP11:DA11) -> 885 | DD11: =SUM(O11+AB11+AO11+BB11+BO11+CB11+CO11+DB11) -> 12852
B12: NEULASTIM | C12: 0 | D12: 0 | E12: 0 | F12: 0 | G12: 0 | H12: 0 | I12: 0 | J12: 0 | K12: 0 | L12: 0 | M12: 0 | N12: 0 | O12: =+SUM(C12:N12) -> 0 | P12: 0 | Q12: 0 | R12: 0 | S12: 0 | T12: 0 | U12: 0 | V12: 0 | W12: 0 | X12: 0 | Y12: 0 | Z12: 0 | AA12: 0 | AB12: =SUM($P12:$AA12) -> 0 | AC12: 215 | AD12: 155 | AE12: 193 | AF12: 253 | AG12: 228 | AH12: 228 | AI12: 246 | AJ12: 334 | AK12: 336 | AL12: 292 | AM12: 339 | AN12: 267 | AO12: =SUM(AC12:AN12) -> 3086 | AP12: 300 | AQ12: 215 | AR12: 302 | AS12: 319 | AT12: 284 | AU12: 260 | AV12: 337 | AW12: 285 | AX12: 210 | AY12: 275 | AZ12: 228 | BA12: 300 | BB12: =SUM(AP12:BA12) -> 3315 | BC12: 267 | BD12: 214 | BE12: 256 | BF12: 235 | BG12: 264 | BH12: 251 | BI12: 272 | BJ12: 236 | BK12: 313 | BL12: 245 | BM12: 224 | BN12: 265 | BO12: =SUM(BC12:BN12) -> 3042 | BP12: 172 | BQ12: 167 | BR12: 195 | BS12: 129 | BT12: 136 | BU12: 167 | BV12: 232 | BW12: 183 | BX12: 244 | BY12: 213 | BZ12: 225 | CA12: 206 | CB12: =SUM(BP12:CA12) -> 2269 | CC12: 237 | CD12: 145 | CE12: 221 | CF12: 144 | CG12: 152 | CH12: 139 | CI12: 126 | CJ12: 163 | CK12: 177 | CL12: 182 | CM12: 137 | CN12: 175 | CO12: =SUM(CC12:CN12) -> 1998 | CP12: 167 | CQ12: 130 | CR12: 144 | CS12: 139 | CT12: 159 | DB12: =SUM(CP12:DA12) -> 739 | DD12: =SUM(O12+AB12+AO12+BB12+BO12+CB12+CO12+DB12) -> 14449
B13: MIMPARA | C13: 9 | D13: 44 | E13: 62 | F13: 40 | G13: 48 | H13: 59 | I13: 64 | J13: 63 | K13: 88 | L13: 111 | M13: 103 | N13: 98 | O13: =+SUM(C13:N13) -> 789 | P13: 106 | Q13: 111 | R13: 97 | S13: 107 | T13: 101 | U13: 95 | V13: 120 | W13: 140 | X13: 100 | Y13: 145 | Z13: 146 | AA13: 159 | AB13: =SUM($P13:$AA13) -> 1427 | AC13: 143 | AD13: 143 | AE13: 189 | AF13: 168 | AG13: 188 | AH13: 158 | AI13: 157 | AJ13: 174 | AK13: 157 | AL13: 191 | AM13: 178 | AN13: 170 | AO13: =SUM(AC13:AN13) -> 2016 | AP13: 176 | AQ13: 263 | AR13: 194 | AS13: 188 | AT13: 209 | AU13: 170 | AV13: 157 | AW13: 151 | AX13: 142 | AY13: 142 | AZ13: 136 | BA13: 169 | BB13: =SUM(AP13:BA13) -> 2097 | BC13: 112 | BD13: 101 | BE13: 135 | BF13: 123 | BG13: 149 | BH13: 170 | BI13: 199 | BJ13: 134 | BK13: 183 | BL13: 162 | BM13: 177 | BN13: 144 | BO13: =SUM(BC13:BN13) -> 1789 | BP13: 142 | BQ13: 137 | BR13: 168 | BS13: 133 | BT13: 168 | BU13: 150 | BV13: 127 | BW13: 151 | BX13: 141 | BY13: 129 | BZ13: 135 | CA13: 152 | CB13: =SUM(BP13:CA13) -> 1733 | CC13: 129 | CD13: 137 | CE13: 150 | CF13: 144 | CG13: 132 | CH13: 145 | CI13: 158 | CJ13: 132 | CK13: 136 | CL13: 155 | CM13: 121 | CN13: 119 | CO13: =SUM(CC13:CN13) -> 1658 | CP13: 127 | CQ13: 148 | CR13: 133 | CS13: 151 | CT13: 133 | DB13: =SUM(CP13:DA13) -> 692 | DD13: =SUM(O13+AB13+AO13+BB13+BO13+CB13+CO13+DB13) -> 12201
B14: XGEVA | C14: 0 | D14: 0 | E14: 0 | F14: 0 | G14: 0 | H14: 0 | I14: 0 | J14: 0 | K14: 0 | L14: 0 | M14: 0 | N14: 0 | O14: =+SUM(C14:N14) -> 0 | P14: 0 | Q14: 0 | R14: 0 | S14: 0 | T14: 0 | U14: 0 | V14: 0 | W14: 23 | X14: 58 | Y14: 102 | Z14: 92 | AA14: 88 | AB14: =SUM($P14:$AA14) -> 363 | AC14: 124 | AD14: 118 | AE14: 147 | AF14: 160 | AG14: 152 | AH14: 171 | AI14: 183 | AJ14: 209 | AK14: 165 | AL14: 220 | AM14: 236 | AN14: 200 | AO14: =SUM(AC14:AN14) -> 2085 | AP14: 222 | AQ14: 213 | AR14: 235 | AS14: 234 | AT14: 252 | AU14: 215 | AV14: 260 | AW14: 225 | AX14: 203 | AY14: 203 | AZ14: 190 | BA14: 212 | BB14: =SUM(AP14:BA14) -> 2664 | BC14: 202 | BD14: 216 | BE14: 246 | BF14: 213 | BG14: 219 | BH14: 214 | BI14: 228 | BJ14: 247 | BK14: 258 | BL14: 247 | BM14: 216 | BN14: 219 | BO14: =SUM(BC14:BN14) -> 2725 | BP14: 234 | BQ14: 198 | BR14: 219 | BS14: 222 | BT14: 239 | BU14: 230 | BV14: 219 | BW14: 245 | BX14: 235 | BY14: 246 | BZ14: 199 | CA14: 195 | CB14: =SUM(BP14:CA14) -> 2681 | CC14: 234 | CD14: 197 | CE14: 211 | CF14: 195 | CG14: 226 | CH14: 184 | CI14: 205 | CJ14: 199 | CK14: 182 | CL14: 218 | CM14: 207 | CN14: 202 | CO14: =SUM(CC14:CN14) -> 2460 | CP14: 212 | CQ14: 221 | CR14: 210 | CS14: 220 | CT14: 229 | DB14: =SUM(CP14:DA14) -> 1092 | DD14: =SUM(O14+AB14+AO14+BB14+BO14+CB14+CO14+DB14) -> 14070
B15: VECTIBIX | C15: 0 | D15: 0 | E15: 0 | F15: 0 | G15: 0 | H15: 0 | I15: 0 | J15: 0 | K15: 24 | L15: 61 | M15: 89 | N15: 57 | O15: =+SUM(C15:N15) -> 231 | P15: 62 | Q15: 81 | R15: 58 | S15: 72 | T15: 72 | U15: 89 | V15: 129 | W15: 155 | X15: 73 | Y15: 63 | Z15: 117 | AA15: 110 | AB15: =SUM($P15:$AA15) -> 1081 | AC15: 100 | AD15: 86 | AE15: 81 | AF15: 90 | AG15: 92 | AH15: 118 | AI15: 155 | AJ15: 152 | AK15: 160 | AL15: 136 | AM15: 243 | AN15: 125 | AO15: =SUM(AC15:AN15) -> 1538 | AP15: 224 | AQ15: 159 | AR15: 171 | AS15: 204 | AT15: 170 | AU15: 156 | AV15: 235 | AW15: 125 | AX15: 78 | AY15: 77 | AZ15: 82 | BA15: 153 | BB15: =SUM(AP15:BA15) -> 1834 | BC15: 130 | BD15: 156 | BE15: 87 | BF15: 161 | BG15: 80 | BH15: 103 | BI15: 142 | BJ15: 87 | BK15: 156 | BL15: 201 | BM15: 148 | BN15: 104 | BO15: =SUM(BC15:BN15) -> 1555 | BP15: 90 | BQ15: 93 | BR15: 70 | BS15: 54 | BT15: 57 | BU15: 66 | BV15: 59 | BW15: 39 | BX15: 36 | BY15: 40 | BZ15: 75 | CA15: 63 | CB15: =SUM(BP15:CA15) -> 742 | CC15: 54 | CD15: 92 | CE15: 60 | CF15: 67 | CG15: 70 | CH15: 76 | CI15: 67 | CJ15: 44 | CK15: 54 | CL15: 47 | CM15: 68 | CN15: 46 | CO15: =SUM(CC15:CN15) -> 745 | CP15: 54 | CQ15: 50 | CR15: 68 | CS15: 77 | CT15: 102 | DB15: =SUM(CP15:DA15) -> 351 | DD15: =SUM(O15+AB15+AO15+BB15+BO15+CB15+CO15+DB15) -> 8077
B16: REPATHA | C16: 0 | D16: 0 | E16: 0 | F16: 0 | G16: 0 | H16: 0 | I16: 0 | J16: 0 | K16: 0 | L16: 0 | M16: 0 | N16: 0 | O16: =+SUM(C16:N16) -> 0 | P16: 0 | Q16: 0 | R16: 0 | S16: 0 | T16: 0 | U16: 0 | V16: 0 | W16: 0 | X16: 0 | Y16: 0 | Z16: 0 | AA16: 0 | AB16: =SUM($P16:$AA16) -> 0 | AC16: 0 | AD16: 0 | AE16: 0 | AF16: 0 | AG16: 0 | AH16: 0 | AI16: 0 | AJ16: 0 | AK16: 0 | AL16: 0 | AM16: 0 | AN16: 0 | AO16: =SUM(AC16:AN16) -> 0 | AP16: 0 | AQ16: 0 | AR16: 0 | AS16: 0 | AT16: 0 | AU16: 0 | AV16: 0 | AW16: 0 | AX16: 0 | AY16: 0 | AZ16: 0 | BA16: 0 | BB16: =SUM(AP16:BA16) -> 0 | BC16: 0 | BD16: 0 | BE16: 0 | BF16: 0 | BG16: 0 | BH16: 0 | BI16: 0 | BJ16: 0 | BK16: 0 | BL16: 0 | BM16: 0 | BN16: 0 | BO16: =SUM(BC16:BN16) -> 0 | BP16: 0 | BQ16: 0 | BR16: 0 | BS16: 0 | BT16: 0 | BU16: 0 | BV16: 50 | BW16: 78 | BX16: 85 | BY16: 93 | BZ16: 125 | CA16: 188 | CB16: =SUM(BP16:CA16) -> 619 | CC16: 209 | CD16: 216 | CE16: 312 | CF16: 282 | CG16: 335 | CH16: 374 | CI16: 368 | CJ16: 453 | CK16: 410 | CL16: 424 | CM16: 362 | CN16: 405 | CO16: =SUM(CC16:CN16) -> 4150 | CP16: 332 | CQ16: 356 | CR16: 387 | CS16: 377 | CT16: 431 | DB16: =SUM(CP16:DA16) -> 1883 | DD16: =SUM(O16+AB16+AO16+BB16+BO16+CB16+CO16+DB16) -> 6652
B17: BLINCYTO | C17: 0 | D17: 0 | E17: 0 | F17: 0 | G17: 0 | H17: 0 | I17: 0 | J17: 0 | K17: 0 | L17: 0 | M17: 0 | N17: 0 | O17: =+SUM(C17:N17) -> 0 | P17: 0 | Q17: 0 | R17: 0 | S17: 0 | T17: 0 | U17: 0 | V17: 0 | W17: 0 | X17: 0 | Y17: 0 | Z17: 0 | AA17: 0 | AB17: =SUM($P17:$AA17) -> 0 | AC17: 0 | AD17: 0 | AE17: 0 | AF17: 0 | AG17: 0 | AH17: 0 | AI17: 0 | AJ17: 0 | AK17: 0 | AL17: 0 | AM17: 0 | AN17: 0 | AO17: =SUM(AC17:AN17) -> 0 | AP17: 0 | AQ17: 0 | AR17: 0 | AS17: 0 | AT17: 0 | AU17: 0 | AV17: 0 | AW17: 0 | AX17: 0 | AY17: 0 | AZ17: 0 | BA17: 0 | BB17: =SUM(AP17:BA17) -> 0 | BC17: 0 | BD17: 0 | BE17: 0 | BF17: 0 | BG17: 0 | BH17: 0 | BI17: 0 | BJ17: 0 | BK17: 0 | BL17: 0 | BM17: 0 | BN17: 0 | BO17: =SUM(BC17:BN17) -> 0 | BP17: 0 | BQ17: 0 | BR17: 0 | BS17: 0 | BT17: 10 | BU17: 9 | BV17: 0 | BW17: 0 | BX17: 6 | BY17: 12 | BZ17: 31 | CA17: 1 | CB17: =SUM(BP17:CA17) -> 69 | CC17: 0 | CD17: 17 | CE17: 20 | CF17: 39 | CG17: 31 | CH17: 10 | CI17: 23 | CJ17: 64 | CK17: 33 | CL17: 5 | CM17: 37 | CN17: 61 | CO17: =SUM(CC17:CN17) -> 340 | CP17: 88 | CQ17: 30 | CR17: 37 | CS17: 30 | CT17: 20 | DB17: =SUM(CP17:DA17) -> 205 | DD17: =SUM(O17+AB17+AO17+BB17+BO17+CB17+CO17+DB17) -> 614
B18: KYPROLIS | C18: 0 | D18: 0 | E18: 0 | F18: 0 | G18: 0 | H18: 0 | I18: 0 | J18: 0 | K18: 0 | L18: 0 | M18: 0 | N18: 0 | O18: =+SUM(C18:N18) -> 0 | P18: 0 | Q18: 0 | R18: 0 | S18: 0 | T18: 0 | U18: 0 | V18: 0 | W18: 0 | X18: 0 | Y18: 0 | Z18: 0 | AA18: 0 | AB18: =SUM($P18:$AA18) -> 0 | AC18: 0 | AD18: 0 | AE18: 0 | AF18: 0 | AG18: 0 | AH18: 0 | AI18: 0 | AJ18: 0 | AK18: 0 | AL18: 0 | AM18: 0 | AN18: 0 | AO18: =SUM(AC18:AN18) -> 0 | AP18: 0 | AQ18: 0 | AR18: 0 | AS18: 0 | AT18: 0 | AU18: 0 | AV18: 0 | AW18: 0 | AX18: 0 | AY18: 0 | AZ18: 0 | BA18: 21 | BB18: =SUM(AP18:BA18) -> 21 | BC18: 28 | BD18: 46 | BE18: 46 | BF18: 61 | BG18: 47 | BH18: 66 | BI18: 59 | BJ18: 58 | BK18: 48 | BL18: 67 | BM18: 74 | BN18: 60 | BO18: =SUM(BC18:BN18) -> 660 | BP18: 52 | BQ18: 43 | BR18: 39 | BS18: 47 | BT18: 77 | BU18: 83 | BV18: 56 | BW18: 86 | BX18: 34 | BY18: 21 | BZ18: 36 | CA18: 51 | CB18: =SUM(BP18:CA18) -> 625 | CC18: 24 | CD18: 19 | CE18: 27 | CF18: 32 | CG18: 26 | CH18: 29 | CI18: 41 | CJ18: 44 | CK18: 33 | CL18: 28 | CM18: 44 | CN18: 59 | CO18: =SUM(CC18:CN18) -> 406 | CP18: 61 | CQ18: 77 | CR18: 51 | CS18: 56 | CT18: 47 | DB18: =SUM(CP18:DA18) -> 292 | DD18: =SUM(O18+AB18+AO18+BB18+BO18+CB18+CO18+DB18) -> 2004
B19: Total general | C19: =SUM(C8:C18) -> 9 | D19: =SUM(D8:D18) -> 50 | E19: =SUM(E8:E18) -> 67 | F19: =SUM(F8:F18) -> 49 | G19: =SUM(G8:G18) -> 81 | H19: =SUM(H8:H18) -> 103 | I19: =SUM(I8:I18) -> 119 | J19: =SUM(J8:J18) -> 121 | ... N19: =SUM(N8:N18) -> 318 | O19: =IF(SUM(O8:O18)=SUM(C19:N19),SUM(O8:O18),"ERROR") -> 1739 | P19: =SUM(P8:P18) -> 315 | Q19: =SUM(Q8:Q18) -> 403 | R19: =SUM(R8:R18) -> 424 | S19: =SUM(S8:S18) -> 479 | T19: =SUM(T8:T18) -> 517 | U19: =SUM(U8:U18) -> 575 | V19: =SUM(V8:V18) -> 750 | W19: =SUM(W8:W18) -> 931 | ... AA19: =SUM(AA8:AA18) -> 1020 | AB19: =IF(SUM($P$19:$AA$19)=SUM($AB$8:$AB$18),SUM($P$19:$AA$19),"ERROR") -> 8290 | AC19: =SUM(AC8:AC18) -> 2420 | AD19: =SUM(AD8:AD18) -> 2009 | AE19: =SUM(AE8:AE18) -> 2508 | AF19: =SUM(AF8:AF18) -> 2848 | AG19: =SUM(AG8:AG18) -> 2737 | AH19: =SUM(AH8:AH18) -> 2784 | AI19: =SUM(AI8:AI18) -> 3217 | AJ19: =SUM(AJ8:AJ18) -> 3055 | ... AN19: =SUM(AN8:AN18) -> 2710 | AO19: =IF(SUM($AC$19:$AN$19)=SUM($AO$8:$AO$18),SUM($AC$19:AN$19),"ERROR") -> 33690 | AP19: =SUM(AP8:AP18) -> 3079 | AQ19: =SUM(AQ8:AQ18) -> 2941 | AR19: =SUM(AR8:AR18) -> 3146 | AS19: =SUM(AS8:AS18) -> 3290 | AT19: =SUM(AT8:AT18) -> 3539 | AU19: =SUM(AU8:AU18) -> 3163 | AV19: =SUM(AV8:AV18) -> 3667 | AW19: =SUM(AW8:AW18) -> 3354 | ... BA19: =SUM(BA8:BA18) -> 3573 | BB19: =IF(SUM(AP19:BA19)=SUM($BB$8:$BB$18),SUM(AP19:BA19),"ERROR") -> 38688 | BC19: =SUM(BC8:BC18) -> 3193 | BD19: =SUM(BD8:BD18) -> 3001 | BE19: =SUM(BE8:BE18) -> 3453 | BF19: =SUM(BF8:BF18) -> 3338 | BG19: =SUM(BG8:BG18) -> 3230 | BH19: =SUM(BH8:BH18) -> 3571 | BI19: =SUM(BI8:BI18) -> 3785 | BJ19: =SUM(BJ8:BJ18) -> 3205 | ... BN19: =SUM(BN8:BN18) -> 3601 | BO19: =IF(SUM(BC19:BN19)=SUM($BO$8:$BO$18),SUM(BC19:BN19),"ERROR") -> 41950 | BP19: =SUM(BP8:BP18) -> 3359 | BQ19: =SUM(BQ8:BQ18) -> 3393 | BR19: =SUM(BR8:BR18) -> 3614 | BS19: =SUM(BS8:BS18) -> 3229 | BT19: =SUM(BT8:BT18) -> 3211 | BU19: =SUM(BU8:BU18) -> 3686 | BV19: =SUM(BV8:BV18) -> 3682 | BW19: =SUM(BW8:BW18) -> 3860 | ... CA19: =SUM(CA8:CA18) -> 3708 | CB19: =IF(SUM(BP19:CA19)=SUM($CB$8:$CB$18),SUM(BP19:CA19),"ERROR") -> 42787 | CC19: =SUM(CC8:CC18) -> 3638 | CD19: =SUM(CD8:CD18) -> 3273 | CE19: =SUM(CE8:CE18) -> 3729 | CF19: =SUM(CF8:CF18) -> 3156 | CG19: =SUM(CG8:CG18) -> 3784 | CH19: =SUM(CH8:CH18) -> 3490 | CI19: =SUM(CI8:CI18) -> 3500 | CJ19: =SUM(CJ8:CJ18) -> 3779 | ... CN19: =SUM(CN8:CN18) -> 3483 | CO19: =IF(SUM(CC19:CN19)=SUM($CO$8:$CO$18),SUM(CC19:CN19),"ERROR") -> 42516 | CP19: =SUM(CP8:CP18) -> 3479 | CQ19: =SUM(CQ8:CQ18) -> 3285 | CR19: =SUM(CR8:CR18) -> 3539 | CS19: =SUM(CS8:CS18) -> 3473 | CT19: =SUM(CT8:CT18) -> 3920 | CU19: =SUM(CU8:CU18) -> 0 | CV19: =SUM(CV8:CV18) -> 0 | CW19: =SUM(CW8:CW18) -> 0 | ... DA19: =SUM(DA8:DA18) -> 0 | DB19: =IF(SUM(CP19:DA19)=SUM($DB$8:$DB$18),SUM(CP19:DA19),"ERROR") -> 17696 | DD19: =IF(SUM(DD8:DD18)=SUM(O19+BO19+BB19+AB19+AO19+CB19+CO19+DB19),SUM(DD8:DD18),"ERROR") -> 227356

Sheet Farmacia
B3: MIMPARA, NPLATE, ARANESP, VECTIBIX, PROLIA,REPATHA,BLINCYTO & XGEVA
B4: DESPLAZAMIENTOS POR FARMACIA
B5: ='Resumen General'!B5 -> DEL 01 AL 31 DE MAYO 2018
B8: PRODUCTO | C8: (Todas)
D10: Valores
B11: ESTADO | C11: SUCURSAL | D11: PZAS MES ACT | E11: % PART
B12: DISTRITO FEDERAL | D12: 1336 | E12: 0.34081633
B13: JALISCO | D13: 343 | E13: 0.0875
B14: GUANAJUATO | D14: 244 | E14: 0.062244898
B15: PUEBLA | D15: 239 | E15: 0.060969388
B16: BAJA CALIFORNIA | D16: 196 | E16: 0.05
B17: NUEVO LEON | D17: 153 | E17: 0.039030612
B18: SONORA | D18: 135 | E18: 0.034438776
B19: COAHUILA | D19: 122 | E19: 0.031122449
B20: SAN LUIS POTOSI | D20: 108 | E20: 0.02755102
B21: VERACRUZ | D21: 108 | E21: 0.02755102
B22: ESTADO DE MEXICO | D22: 105 | E22: 0.026785714
B23: SINALOA | D23: 91 | E23: 0.023214286
... B42: Total general | D42: 3920 | E42: 1

Sheet Tipo de Cliente
B3: MIMPARA, NPLATE, ARANESP, VECTIBIX, PROLIA,REPATHA,BLINCYTO & XGEVA
B4: DESPLAZAMIENTOS POR TIPO DE CLIENTE Y CLIENTE
B5: ='Resumen General'!B5 -> DEL 01 AL 31 DE MAYO 2018
B8: PRODUCTO | C8: (Todas)
C10: Valores
B11: Tipo Cliente / Cliente | C11: PZAS MES ACT | D11: % PART | G11: CLIENTE | H11: DESCRIPCION
B12: MOSTRADOR | C12: 2043 | D12: 0.52117347 | G12: B Y A | H12: CLIENTES REFERIDOS DE BANCOS Y ASEGURADORAS (Ejemplo: GNP,AXXA,BANORTE,VITAMEDICA).
B13: PARTICULARES | C13: 1087 | D13: 0.27729592 | G13: MOSTRADOR | H13: CLIENTES DE PAGO EN EFECTIVO o TARJETA DE CREDITO
B14: B Y A | C14: 774 | D14: 0.19744898 | G14: PARTICULARES | H14: HOSPITALES, INSTITUCIONES, EMPRESAS, CLINICAS, ETC. (Ejemplo:SANATORIO DURANGO,CLINICA DE MERIDA,HOSPITAL ESPAÑOL).
B15: DESCENTRALIZADOS | C15: 15 | D15: 0.0038265306 | G15: SUBROGADOS | H15: CLIENTES CON SUBROGACIONES PERTENECIENTES A ALGUN BOTIQUIN ((Ejemplo:PBI,LOTERIA NACIONAL,NACIONAL MONTE DE PIEDAD).
B16: VACUNAS | C16: 1 | D16: 0.00025510204 | G16: INTERFARMACIA | H16: VALES CANJEADOS A PACIENTES DEL ISSSTE
B17: Total general | C17: 3920 | D17: 1

Sheet Venta Por Canal
B2: MIMPARA, NPLATE, ARANESP, VECTIBIX, PROLIA,REPATHA,BLINCYTO & XGEVA
B3: VENTA POR CANAL
B4: ='Resumen General'!B5 -> DEL 01 AL 31 DE MAYO 2018
B7: PRODUCTO | C7: VENTA TOTAL | D7: VENTA MOSTRADOR | E7: % PART. MOSTRADOR | F7: PEDIDOS TELEFARMACOS | G7: % PART. PED TELEFARMACOS
B8: ARANESP 300MCG/0.6ML JPRELL CAJ C/1 | C8: =SUMIF('Data Venta Total'!D:D,'Venta Por Canal'!B8,'Data Venta Total'!L:L) -> 89 | D8: =C8-F8 -> 37 | E8: =IFERROR(IF(D8/$C8=0,0,D8/$C8),0) -> 0.41573034 | F8: =SUMIF('Data Ped Telefarmacos'!D:D,'Venta Por Canal'!B8,'Data Ped Telefarmacos'!M:M) -> 52 | G8: =IFERROR(IF(F8/$C8=0,0,F8/$C8),0) -> 0.58426966
B9: ARANESP 30MCG/0.3ML JPRELL CAJ C/4 | C9: =SUMIF('Data Venta Total'!D:D,'Venta Por Canal'!B9,'Data Venta Total'!L:L) -> 14 | D9: =C9-F9 -> 8 | E9: =IFERROR(IF(D9/$C9=0,0,D9/$C9),0) -> 0.57142857 | F9: =SUMIF('Data Ped Telefarmacos'!D:D,'Venta Por Canal'!B9,'Data Ped Telefarmacos'!M:M) -> 6 | G9: =IFERROR(IF(F9/$C9=0,0,F9/$C9),0) -> 0.42857143
B10: ARANESP 40MCG/0.4ML JPRELL CAJ C/4 | C10: =SUMIF('Data Venta Total'!D:D,'Venta Por Canal'!B10,'Data Venta Total'!L:L) -> 53 | D10: =C10-F10 -> 37 | E10: =IFERROR(IF(D10/$C10=0,0,D10/$C10),0) -> 0.69811321 | F10: =SUMIF('Data Ped Telefarmacos'!D:D,'Venta Por Canal'!B10,'Data Ped Telefarmacos'!M:M) -> 16 | G10: =IFERROR(IF(F10/$C10=0,0,F10/$C10),0) -> 0.30188679
B11: ARANESP 500MCG/1ML JPRELL CAJ C/1 | C11: =SUMIF('Data Venta Total'!D:D,'Venta Por Canal'!B11,'Data Venta Total'!L:L) -> 98 | D11: =C11-F11 -> 47 | E11: =IFERROR(IF(D11/$C11=0,0,D11/$C11),0) -> 0.47959184 | F11: =SUMIF('Data Ped Telefarmacos'!D:D,'Venta Por Canal'!B11,'Data Ped Telefarmacos'!M:M) -> 51 | G11: =IFERROR(IF(F11/$C11=0,0,F11/$C11),0) -> 0.52040816
B12: ARANESP 60MCG/0.3ML JPRELL CAJ C/4 | C12: =SUMIF('Data Venta Total'!D:D,'Venta Por Canal'!B12,'Data Venta Total'!L:L) -> 77 | D12: =C12-F12 -> 50 | E12: =IFERROR(IF(D12/$C12=0,0,D12/$C12),0) -> 0.64935065 | F12: =SUMIF('Data Ped Telefarmacos'!D:D,'Venta Por Canal'!B12,'Data Ped Telefarmacos'!M:M) -> 27 | G12: =IFERROR(IF(F12/$C12=0,0,F12/$C12),0) -> 0.35064935
B13: ARANESP 80MCG/0.4ML JGP CAJ C/1 | C13: =SUMIF('Data Venta Total'!D:D,'Venta Por Canal'!B13,'Data Venta Total'!L:L) -> 87 | D13: =C13-F13 -> 52 | E13: =IFERROR(IF(D13/$C13=0,0,D13/$C13),0) -> 0.59770115 | F13: =SUMIF('Data Ped Telefarmacos'!D:D,'Venta Por Canal'!B13,'Data Ped Telefarmacos'!M:M) -> 35 | G13: =IFERROR(IF(F13/$C13=0,0,F13/$C13),0) -> 0.40229885
B14: BLINCYTO 35MCG FAM CAJ C/1 | C14: =SUMIF('Data Venta Total'!D:D,'Venta Por Canal'!B14,'Data Venta Total'!L:L) -> 20 | D14: =C14-F14 -> 0 | E14: =IFERROR(IF(D14/$C14=0,0,D14/$C14),0) -> 0 | F14: =SUMIF('Data Ped Telefarmacos'!D:D,'Venta Por Canal'!B14,'Data Ped Telefarmacos'!M:M) -> 20 | G14: =IFERROR(IF(F14/$C14=0,0,F14/$C14),0) -> 1
B15: KYPROLIS 60MG FAM CAJ C/1 | C15: =SUMIF('Data Venta Total'!D:D,'Venta Por Canal'!B15,'Data Venta Total'!L:L) -> 47 | D15: =C15-F15 -> 21 | E15: =IFERROR(IF(D15/$C15=0,0,D15/$C15),0) -> 0.44680851 | F15: =SUMIF('Data Ped Telefarmacos'!D:D,'Venta Por Canal'!B15,'Data Ped Telefarmacos'!M:M) -> 26 | G15: =IFERROR(IF(F15/$C15=0,0,F15/$C15),0) -> 0.55319149
B16: MIMPARA 30MG TAB CAJ C/30 | C16: =SUMIF('Data Venta Total'!D:D,'Venta Por Canal'!B16,'Data Venta Total'!L:L) -> 133 | D16: =C16-F16 -> 99 | E16: =IFERROR(IF(D16/$C16=0,0,D16/$C16),0) -> 0.7443609 | F16: =SUMIF('Data Ped Telefarmacos'!D:D,'Venta Por Canal'!B16,'Data Ped Telefarmacos'!M:M) -> 34 | G16: =IFERROR(IF(F16/$C16=0,0,F16/$C16),0) -> 0.2556391
B17: NEULASTIM 6 mg/0.6 ml JGP CAJ C/1 | C17: =SUMIF('Data Venta Total'!D:D,'Venta Por Canal'!B17,'Data Venta Total'!L:L) -> 159 | D17: =C17-F17 -> 110 | E17: =IFERROR(IF(D17/$C17=0,0,D17/$C17),0) -> 0.6918239 | F17: =SUMIF('Data Ped Telefarmacos'!D:D,'Venta Por Canal'!B17,'Data Ped Telefarmacos'!M:M) -> 49 | G17: =IFERROR(IF(F17/$C17=0,0,F17/$C17),0) -> 0.3081761
B18: NEUPOGEN 300 mcg/0.5 ml 1 JGP C/0.5 ml | C18: =SUMIF('Data Venta Total'!D:D,'Venta Por Canal'!B18,'Data Venta Total'!L:L) -> 727 | D18: =C18-F18 -> 310 | E18: =IFERROR(IF(D18/$C18=0,0,D18/$C18),0) -> 0.4264099 | F18: =SUMIF('Data Ped Telefarmacos'!D:D,'Venta Por Canal'!B18,'Data Ped Telefarmacos'!M:M) -> 417 | G18: =IFERROR(IF(F18/$C18=0,0,F18/$C18),0) -> 0.5735901
B19: NPLATE 250 mcg FAM C/1 | C19: =SUMIF('Data Venta Total'!D:D,'Venta Por Canal'!B19,'Data Venta Total'!L:L) -> 171 | D19: =C19-F19 -> 95 | E19: =IFERROR(IF(D19/$C19=0,0,D19/$C19),0) -> 0.55555556 | F19: =SUMIF('Data Ped Telefarmacos'!D:D,'Venta Por Canal'!B19,'Data Ped Telefarmacos'!M:M) -> 76 | G19: =IFERROR(IF(F19/$C19=0,0,F19/$C19),0) -> 0.44444444
... B23: XGEVA 120MG/1.7ML F A CAJ C/1 | C23: =SUMIF('Data Venta Total'!D:D,'Venta Por Canal'!B23,'Data Venta Total'!L:L) -> 229 | D23: =C23-F23 -> 123 | E23: =IFERROR(IF(D23/$C23=0,0,D23/$C23),0) -> 0.5371179 | F23: =SUMIF('Data Ped Telefarmacos'!D:D,'Venta Por Canal'!B23,'Data Ped Telefarmacos'!M:M) -> 106 | G23: =IFERROR(IF(F23/$C23=0,0,F23/$C23),0) -> 0.4628821
B24: Total | C24: =SUM(C8:C23) -> 3920 | D24: =C24-F24 -> 2119 | E24: =IFERROR(IF(D24/$C24=0,0,D24/$C24),0) -> 0.54056122 | F24: =SUM(F8:F23) -> 1801 | G24: =IFERROR(IF(F24/$C24=0,0,F24/$C24),0) -> 0.45943878

Sheet Data Venta Total
B2: MIMPARA, NPLATE, ARANESP, VECTIBIX, PROLIA,REPATHA,BLINCYTO & XGEVA
B3: DATA DE VENTA TOTAL
B4: ='Resumen General'!B5 -> DEL 01 AL 31 DE MAYO 2018
B7: PROGRAMA | C7: FAMILIA | D7: PRODUCTO | E7: SUCURSAL | F7: ESTADO | G7: TIPO DE CLIENTE | H7: CLIENTE | I7: MEDICO | J7: STATUS DE PIEZAS | K7: FECHA DE VENTA | L7: PZAS MES ACTUAL
B8: SIN PROGRAMA | C8: ARANESP | D8: ARANESP 300MCG/0.6ML JPRELL CAJ C/1 | E8: TLACOTALPAN | F8: DISTRITO FEDERAL | G8: PARTICULARES | H8: HOSPITAL ESPAÑOL | I8: HOSPITAL ESPAÑOL | J8: VENTA | K8: 43221 | L8: 1
B9: SIN PROGRAMA | C9: ARANESP | D9: ARANESP 300MCG/0.6ML JPRELL CAJ C/1 | E9: BOTIQUIN HOSPITAL ABC | F9: DISTRITO FEDERAL | G9: PARTICULARES | H9: BOTIQUIN HOSPITAL ABC | I9: SIN INFORMACION | J9: VENTA | K9: 43221 | L9: 2
B10: SIN PROGRAMA | C10: ARANESP | D10: ARANESP 300MCG/0.6ML JPRELL CAJ C/1 | E10: LEON | F10: GUANAJUATO | G10: MOSTRADOR | H10: EFECTIVO | I10: SIN INFORMACION | J10: VENTA | K10: 43222 | L10: 1
B11: SIN PROGRAMA | C11: ARANESP | D11: ARANESP 300MCG/0.6ML JPRELL CAJ C/1 | E11: ESCANDON | F11: DISTRITO FEDERAL | G11: B Y A | H11: INTEGRAMED | I11: ENRIQUEZ LUIS ENRIQUE | J11: VENTA | K11: 43223 | L11: 3
B12: SIN PROGRAMA | C12: ARANESP | D12: ARANESP 300MCG/0.6ML JPRELL CAJ C/1 | E12: TLALPAN | F12: DISTRITO FEDERAL | G12: PARTICULARES | H12: OPERADORA DE HOSPITALES ANGELES (TLALPAN) | I12: OPERADORA DE HOSPITALES ANGELES (PEDREGAL) | J12: VENTA | K12: 43223 | L12: 1
B13: SIN PROGRAMA | C13: ARANESP | D13: ARANESP 300MCG/0.6ML JPRELL CAJ C/1 | E13: CULIACAN | F13: SINALOA | G13: B Y A | H13: AXA SEGUROS (GASTOS MEDICOS MAYORES) | I13: LOPEZ LORBEN | J13: VENTA | K13: 43224 | L13: 1
B14: SIN PROGRAMA | C14: ARANESP | D14: ARANESP 300MCG/0.6ML JPRELL CAJ C/1 | E14: BOTIQUIN HOSPITAL ABC | F14: DISTRITO FEDERAL | G14: PARTICULARES | H14: BOTIQUIN HOSPITAL ABC | I14: SIN INFORMACION | J14: VENTA | K14: 43224 | L14: 2
B15: SIN PROGRAMA | C15: ARANESP | D15: ARANESP 300MCG/0.6ML JPRELL CAJ C/1 | E15: TLACOTALPAN | F15: DISTRITO FEDERAL | G15: PARTICULARES | H15: OPERADORA DE HOSPITALES ANGELES (GINECO OBSTETRICA) | I15: OPERADORA DE HOSPITALES ANGELES (GINECO OBSTETRICA) | J15: VENTA | K15: 43226 | L15: 1
B16: SIN PROGRAMA | C16: ARANESP | D16: ARANESP 300MCG/0.6ML JPRELL CAJ C/1 | E16: DIVISION DEL NORTE | F16: DISTRITO FEDERAL | G16: MOSTRADOR | H16: EFECTIVO | I16: SIN INFORMACION | J16: VENTA | K16: 43227 | L16: 10
B17: SIN PROGRAMA | C17: ARANESP | D17: ARANESP 300MCG/0.6ML JPRELL CAJ C/1 | E17: PUEBLA 3 | F17: PUEBLA | G17: PARTICULARES | H17: OPERADORA DE HOSPITALES ANGELES (PUEBLA 3) | I17: OPERADORA DE HOSPITALES ANGELES (PUEBLA 3) | J17: VENTA | K17: 43227 | L17: 4
B18: SIN PROGRAMA | C18: ARANESP | D18: ARANESP 300MCG/0.6ML JPRELL CAJ C/1 | E18: TLACOTALPAN | F18: DISTRITO FEDERAL | G18: PARTICULARES | H18: STAR MEDICA (SANTA FE) | I18: STAR MEDICA (CENTRO) | J18: VENTA | K18: 43227 | L18: 1
B19: SIN PROGRAMA | C19: ARANESP | D19: ARANESP 300MCG/0.6ML JPRELL CAJ C/1 | E19: DIVISION DEL NORTE | F19: DISTRITO FEDERAL | G19: MOSTRADOR | H19: EFECTIVO | I19: SIN INFORMACION | J19: VENTA | K19: 43229 | L19: 1
... B2760: SIN PROGRAMA | C2760: XGEVA | D2760: XGEVA 120MG/1.7ML F A CAJ C/1 | E2760: SANATORIO DURANGO | F2760: DISTRITO FEDERAL | G2760: B Y A | H2760: BBVA BANCOMER OPERADORA | I2760: SIN INFORMACION | J2760: VENTA | K2760: 43251 | L2760: 1
K2761: Total General | L2761: =SUBTOTAL(109,Tabla3[PZAS MES ACTUAL]) -> 3920

Sheet Data Ped Telefarmacos
B2: ='Resumen General'!B3 -> MIMPARA, NPLATE, ARANESP, VECTIBIX, PROLIA,REPATHA,BLINCYTO & XGEVA
B3: DATA DE PEDIDOS TELEFARMACOS
B4: ='Resumen General'!B5 -> DEL 01 AL 31 DE MAYO 2018
B7: CANAL VENTA | C7: FAMILIA | D7: PRODUCTO | E7: PEDIDO TELEFARMACOS | F7: CVE PACIENTE | G7: CVE MEDICO | H7: MEDICO | I7: ESPECIALIDAD | J7: SUCURSAL | K7: PROGRAMA | L7: TIPO DE VENTA | M7: PIEZAS | N7: FECHA DE PEDIDO
B8: PARTICULARES | C8: ARANESP | D8: ARANESP 300MCG/0.6ML JPRELL CAJ C/1 | E8: 1-42916 | F8: 105 | G8: 105 | H8: HOSPITAL ESPAÑOL | I8: SIN INFORMACION | J8: TLACOTALPAN | K8: SIN PROGRAMA | L8: VENTA | M8: 1 | N8: 43221
B9: MOSTRADOR | C9: ARANESP | D9: ARANESP 500MCG/1ML JPRELL CAJ C/1 | E9: 1-42922 | F9: 792914 | G9: 635341 | H9: SIN INFORMACION | I9: SIN INFORMACION | J9: TLALPAN 2 | K9: SIN PROGRAMA | L9: VENTA | M9: 1 | N9: 43221
B10: MOSTRADOR | C10: ARANESP | D10: ARANESP 500MCG/1ML JPRELL CAJ C/1 | E10: 1-41031 | F10: 1051055 | G10: 575156 | H10: LOARCA PIÑA LUIS MARTIN | I10: MEDICINA GENERAL | J10: QUERETARO | K10: SIN PROGRAMA | L10: VENTA | M10: 1 | N10: 43221
B11: PARTICULARES | C11: ARANESP | D11: ARANESP 500MCG/1ML JPRELL CAJ C/1 | E11: 1-42662 | F11: 522 | G11: 522 | H11: OPERADORA DE HOSPITALES ANGELES (PEDREGAL) | I11: SIN INFORMACION | J11: ROMA NORTE | K11: SIN PROGRAMA | L11: VENTA | M11: 1 | N11: 43221
B12: MOSTRADOR | C12: MIMPARA | D12: MIMPARA 30MG TAB CAJ C/30 | E12: 1-32839 | F12: 2460053 | G12: 635341 | H12: SIN INFORMACION | I12: SIN INFORMACION | J12: GUADALAJARA | K12: SIN PROGRAMA | L12: VENTA | M12: 1 | N12: 43221
B13: PARTICULARES | C13: NEULASTIM | D13: NEULASTIM 6 mg/0.6 ml JGP CAJ C/1 | E13: 1-42712 | F13: 532 | G13: 532 | H13: OPERADORA DE HOSPITALES ANGELES (LEON 1 Y 2) | I13: SIN INFORMACION | J13: LEON | K13: SIN PROGRAMA | L13: VENTA | M13: 1 | N13: 43221
B14: MOSTRADOR | C14: NEUPOGEN | D14: NEUPOGEN 300 mcg/0.5 ml 1 JGP C/0.5 ml | E14: 1-41822 | F14: 2953342 | G14: 635341 | H14: SIN INFORMACION | I14: SIN INFORMACION | J14: PRADO NORTE | K14: SIN PROGRAMA | L14: VENTA | M14: 24 | N14: 43221
B15: PARTICULARES | C15: NEUPOGEN | D15: NEUPOGEN 300 mcg/0.5 ml 1 JGP C/0.5 ml | E15: 1-42932 | F15: 564 | G15: 564 | H15: PROMOTORA POBLANA | I15: SIN INFORMACION | J15: PUEBLA 3 | K15: SIN PROGRAMA | L15: VENTA | M15: 3 | N15: 43221
B16: B Y A | C16: NEUPOGEN | D16: NEUPOGEN 300 mcg/0.5 ml 1 JGP C/0.5 ml | E16: 1-34362 | F16: 2952137 | G16: 565046 | H16: CASTAÑEDA OMAR HUMBERTO | I16: MEDICINA GENERAL | J16: SALTILLO | K16: SIN PROGRAMA | L16: VENTA | M16: 5 | N16: 43221
B17: MOSTRADOR | C17: PROLIA | D17: PROLIA 60MG/1ML JPRELL CAJ C/1 | E17: 1-42877 | F17: 2956489 | G17: 635341 | H17: SIN INFORMACION | I17: SIN INFORMACION | J17: GUADALAJARA | K17: SIN PROGRAMA | L17: VENTA | M17: 1 | N17: 43221
B18: MOSTRADOR | C18: PROLIA | D18: PROLIA 60MG/1ML JPRELL CAJ C/1 | E18: 1-9194 | F18: 2935968 | G18: 190740 | H18: HERNANDEZ ALBERTO GUILLERMO | I18: MEDICINA GENERAL | J18: GUADALAJARA | K18: CON PROGRAMA | L18: VENTA | M18: 1 | N18: 43221
B19: MOSTRADOR | C19: PROLIA | D19: PROLIA 60MG/1ML JPRELL CAJ C/1 | E19: 1-40260 | F19: 2955126 | G19: 635341 | H19: SIN INFORMACION | I19: SIN INFORMACION | J19: LOS MOCHIS | K19: SIN PROGRAMA | L19: VENTA | M19: 1 | N19: 43221
... B38: B Y A | C38: XGEVA | D38: XGEVA 120MG/1.7ML F A CAJ C/1 | E38: 1-17288 | F38: 643813 | G38: 607242 | H38: HUITZIL MELENDEZ FIDEL DAVID | I38: MEDICINA GENERAL | J38: BOSQUES | K38: SIN PROGRAMA | L38: VENTA | M38: 1 | N38: 43221
B39: B Y A | C39: ARANESP | D39: ARANESP 300MCG/0.6ML JPRELL CAJ C/1 | E39: 1-44547 | F39: 402736 | G39: 568104 | H39: ENRIQUEZ LUIS ENRIQUE | I39: MEDICINA GENERAL | J39: ESCANDON | K39: SIN PROGRAMA | L39: VENTA | M39: 3 | N39: 43222
B40: PARTICULARES | C40: ARANESP | D40: ARANESP 40MCG/0.4ML JPRELL CAJ C/4 | E40: 1-44223 | F40: 391 | G40: 391 | H40: C.I.M.A. (HERMOSILLO) | I40: SIN INFORMACION | J40: HERMOSILLO | K40: SIN PROGRAMA | L40: VENTA | M40: 2 | N40: 43222
B41: B Y A | C41: ARANESP | D41: ARANESP 40MCG/0.4ML JPRELL CAJ C/4 | E41: 1-44979 | F41: 2453883 | G41: 651389 | H41: LOPEZ MARIA OLIMPIA | I41: SIN INFORMACION | J41: PUEBLA | K41: SIN PROGRAMA | L41: VENTA | M41: 1 | N41: 43222
B42: B Y A | C42: ARANESP | D42: ARANESP 60MCG/0.3ML JPRELL CAJ C/4 | E42: 1-43667 | F42: 974529 | G42: 584268 | H42: RODRIGUEZ SILVIA MARGARITA | I42: MEDICINA GENERAL | J42: MERIDA | K42: SIN PROGRAMA | L42: VENTA | M42: 1 | N42: 43222
B43: B Y A | C43: ARANESP | D43: ARANESP 80MCG/0.4ML JGP CAJ C/1 | E43: 1-44788 | F43: 704438 | G43: 734832 | H43: HERNANDEZ ROMAN | I43: NEFROLOGIA | J43: LINDAVISTA | K43: SIN PROGRAMA | L43: VENTA | M43: 1 | N43: 43222
B44: MOSTRADOR | C44: MIMPARA | D44: MIMPARA 30MG TAB CAJ C/30 | E44: 1-44330 | F44: 2957107 | G44: 564519 | H44: CANO PALMEROS MIGUEL ANGEL | I44: MEDICINA INTERNA | J44: VERACRUZ | K44: SIN PROGRAMA | L44: VENTA | M44: 1 | N44: 43222
B45: B Y A | C45: MIMPARA | D45: MIMPARA 30MG TAB CAJ C/30 | E45: 1-44443 | F45: 808529 | G45: 599009 | H45: URZUA GONZALEZ ALBERTO | I45: MEDICINA GENERAL | J45: LA VILLA | K45: SIN PROGRAMA | L45: VENTA | M45: 2 | N45: 43222
B46: B Y A | C46: MIMPARA | D46: MIMPARA 30MG TAB CAJ C/30 | E46: 1-44510 | F46: 402736 | G46: 568104 | H46: ENRIQUEZ LUIS ENRIQUE | I46: MEDICINA GENERAL | J46: ESCANDON | K46: SIN PROGRAMA | L46: VENTA | M46: 2 | N46: 43222
B47: B Y A | C47: MIMPARA | D47: MIMPARA 30MG TAB CAJ C/30 | E47: 1-44788 | F47: 704438 | G47: 734832 | H47: HERNANDEZ ROMAN | I47: NEFROLOGIA | J47: LINDAVISTA | K47: SIN PROGRAMA | L47: VENTA | M47: 1 | N47: 43222
B48: VACUNAS | C48: MIMPARA | D48: MIMPARA 30MG TAB CAJ C/30 | E48: 1-43218 | F48: 3635 | G48: 3635 | H48: NUEVO SANATORIO DURANGO SA DE CV | I48: SIN INFORMACION | J48: ROMA NORTE | K48: SIN PROGRAMA | L48: VENTA | M48: 1 | N48: 43222
B49: PARTICULARES | C49: NEULASTIM | D49: NEULASTIM 6 mg/0.6 ml JGP CAJ C/1 | E49: 1-45042 | F49: 195 | G49: 195 | H49: HOSPITAL DEL PRADO | I49: SIN INFORMACION | J49: TIJUANA 2 | K49: SIN PROGRAMA | L49: VENTA | M49: 1 | N49: 43222
B50: PARTICULARES | C50: NPLATE | D50: NPLATE 250 mcg FAM C/1 | E50: 1-45108 | F50: 525 | G50: 525 | H50: OPERADORA DE HOSPITALES ANGELES (GINECO OBSTETRICA) | I50: SIN INFORMACION | J50: ESCANDON | K50: SIN PROGRAMA | L50: VENTA | M50: 1 | N50: 43222
B51: PARTICULARES | C51: NPLATE | D51: NPLATE 250 mcg FAM C/1 | E51: 1-45114 | F51: 525 | G51: 525 | H51: OPERADORA DE HOSPITALES ANGELES (GINECO OBSTETRICA) | I51: SIN INFORMACION | J51: ESCANDON | K51: SIN PROGRAMA | L51: VENTA | M51: 1 | N51: 43222
B52: MOSTRADOR | C52: PROLIA | D52: PROLIA 60MG/1ML JPRELL CAJ C/1 | E52: 1-43259 | F52: 2956705 | G52: 585591 | H52: SALGADO ADRIANA | I52: MEDICINA GENERAL | J52: CUERNAVACA | K52: SIN PROGRAMA | L52: VENTA | M52: 1 | N52: 43222
B53: MOSTRADOR | C53: PROLIA | D53: PROLIA 60MG/1ML JPRELL CAJ C/1 | E53: 1-43624 | F53: 971812 | G53: 635341 | H53: SIN INFORMACION | I53: SIN INFORMACION | J53: TLALPAN | K53: CON PROGRAMA | L53: VENTA | M53: 1 | N53: 43222
B54: MOSTRADOR | C54: PROLIA | D54: PROLIA 60MG/1ML JPRELL CAJ C/1 | E54: 1-43742 | F54: 973459 | G54: 635341 | H54: SIN INFORMACION | I54: SIN INFORMACION | J54: TLALPAN | K54: SIN PROGRAMA | L54: VENTA | M54: 1 | N54: 43222
B55: MOSTRADOR | C55: PROLIA | D55: PROLIA 60MG/1ML JPRELL CAJ C/1 | E55: 1-43830 | F55: 2956889 | G55: 540467 | H55: ROSEL CARLOS GONZALO | I55: MEDICINA GENERAL | J55: MERIDA | K55: CON PROGRAMA | L55: VENTA | M55: 1 | N55: 43222
B56: MOSTRADOR | C56: PROLIA | D56: PROLIA 60MG/1ML JPRELL CAJ C/1 | E56: 1-43996 | F56: 2956959 | G56: 662923 | H56: DE LA PEÑA RODRIGUEZ MARIA DEL PILAR | I56: SIN INFORMACION | J56: GUADALAJARA | K56: CON PROGRAMA | L56: VENTA | M56: 1 | N56: 43222
B57: MOSTRADOR | C57: PROLIA | D57: PROLIA 60MG/1ML JPRELL CAJ C/1 | E57: 1-44307 | F57: 820789 | G57: 536364 | H57: MADRID CESAR | I57: MEDICINA GENERAL | J57: CHIHUAHUA | K57: CON PROGRAMA | L57: VENTA | M57: 1 | N57: 43222
B58: MOSTRADOR | C58: PROLIA | D58: PROLIA 60MG/1ML JPRELL CAJ C/1 | E58: 1-44370 | F58: 2957144 | G58: 650855 | H58: SILVA HERIBERTO | I58: MEDICINA GENERAL | J58: MONTERREY 4 | K58: SIN PROGRAMA | L58: VENTA | M58: 1 | N58: 43222
... B78: B Y A | C78: PROLIA | D78: PROLIA 60MG/1ML JPRELL CAJ C/1 | E78: 1-44411 | F78: 2957135 | G78: 584483 | H78: RODRIGUEZ FEDERICO LEOPOLDO | I78: MEDICINA GENERAL | J78: BOSQUES | K78: SIN PROGRAMA | L78: VENTA | M78: 1 | N78: 43222
B79: B Y A | C79: PROLIA | D79: PROLIA 60MG/1ML JPRELL CAJ C/1 | E79: 1-44510 | F79: 402736 | G79: 568104 | H79: ENRIQUEZ LUIS ENRIQUE | I79: MEDICINA GENERAL | J79: ESCANDON | K79: SIN PROGRAMA | L79: VENTA | M79: 5 | N79: 43222
B80: B Y A | C80: PROLIA | D80: PROLIA 60MG/1ML JPRELL CAJ C/1 | E80: 1-45106 | F80: 402736 | G80: 568104 | H80: ENRIQUEZ LUIS ENRIQUE | I80: MEDICINA GENERAL | J80: ESCANDON | K80: SIN PROGRAMA | L80: VENTA | M80: 6 | N80: 43222
B81: MOSTRADOR | C81: REPATHA | D81: REPATHA 140MG/ML PLP CAJ C/1 | E81: 1-43784 | F81: 2933669 | G81: 1037626 | H81: GRABER MICHELLE ANDREA | I81: MEDICINA GENERAL | J81: PACHUCA | K81: CON PROGRAMA | L81: VENTA | M81: 1 | N81: 43222
B82: MOSTRADOR | C82: REPATHA | D82: REPATHA 140MG/ML PLP CAJ C/1 | E82: 1-44205 | F82: 2472244 | G82: 2926546 | H82: OROPEZ DANTE | I82: SIN INFORMACION | J82: TORREON | K82: CON PROGRAMA | L82: VENTA | M82: 1 | N82: 43222
B83: PARTICULARES | C83: REPATHA | D83: REPATHA 140MG/ML PLP CAJ C/1 | E83: 1-44247 | F83: 521 | G83: 521 | H83: OPERADORA DE HOSPITALES ANGELES (SANTA ELENA) | I83: SIN INFORMACION | J83: ROMA NORTE | K83: SIN PROGRAMA | L83: VENTA | M83: 1 | N83: 43222
B84: B Y A | C84: REPATHA | D84: REPATHA 140MG/ML PLP CAJ C/1 | E84: 1-43395 | F84: 1112135 | G84: 585558 | H84: SALDANA MENDOZA ARTURO | I84: MEDICINA GENERAL | J84: MAZATLAN | K84: SIN PROGRAMA | L84: VENTA | M84: 2 | N84: 43222
B85: B Y A | C85: REPATHA | D85: REPATHA 140MG/ML PLP CAJ C/1 | E85: 1-45106 | F85: 402736 | G85: 568104 | H85: ENRIQUEZ LUIS ENRIQUE | I85: MEDICINA GENERAL | J85: ESCANDON | K85: SIN PROGRAMA | L85: VENTA | M85: 2 | N85: 43222
B86: PARTICULARES | C86: VECTIBIX | D86: VECTIBIX 100MG/5ML F A CAJ C/1 | E86: 1-44907 | F86: 526 | G86: 526 | H86: OPERADORA DE HOSPITALES ANGELES (MOCEL) | I86: SIN INFORMACION | J86: TLACOTALPAN | K86: SIN PROGRAMA | L86: VENTA | M86: 4 | N86: 43222
B87: MOSTRADOR | C87: XGEVA | D87: XGEVA 120MG/1.7ML F A CAJ C/1 | E87: 1-44019 | F87: 2447958 | G87: 622444 | H87: BARAJAS ROMERO MARCO ANTONIO | I87: MEDICINA GENERAL | J87: GUADALAJARA 3 | K87: SIN PROGRAMA | L87: VENTA | M87: 1 | N87: 43222
B88: B Y A | C88: XGEVA | D88: XGEVA 120MG/1.7ML F A CAJ C/1 | E88: 1-44243 | F88: 1172855 | G88: 608195 | H88: LOPEZ JOSE FRANCISCO | I88: MEDICINA GENERAL | J88: SALTILLO | K88: SIN PROGRAMA | L88: VENTA | M88: 1 | N88: 43222
B89: PARTICULARES | C89: ARANESP | D89: ARANESP 300MCG/0.6ML JPRELL CAJ C/1 | E89: 1-45304 | F89: 522 | G89: 522 | H89: OPERADORA DE HOSPITALES ANGELES (PEDREGAL) | I89: SIN INFORMACION | J89: TLALPAN | K89: SIN PROGRAMA | L89: VENTA | M89: 1 | N89: 43223
B90: MOSTRADOR | C90: ARANESP | D90: ARANESP 500MCG/1ML JPRELL CAJ C/1 | E90: 1-45472 | F90: 807960 | G90: 419361 | H90: OSORIO MARCO ANTONIO | I90: SIN INFORMACION | J90: LEON 2 | K90: SIN PROGRAMA | L90: VENTA | M90: 1 | N90: 43223
B91: PARTICULARES | C91: ARANESP | D91: ARANESP 500MCG/1ML JPRELL CAJ C/1 | E91: 1-46186 | F91: 36016 | G91: 36016 | H91: FLORES Y REGALOS PEDREGAL | I91: SIN INFORMACION | J91: TLALPAN | K91: SIN PROGRAMA | L91: VENTA | M91: 4 | N91: 43223
B92: PARTICULARES | C92: ARANESP | D92: ARANESP 500MCG/1ML JPRELL CAJ C/1 | E92: 1-46216 | F92: 36016 | G92: 36016 | H92: FLORES Y REGALOS PEDREGAL | I92: SIN INFORMACION | J92: TLACOTALPAN | K92: SIN PROGRAMA | L92: VENTA | M92: 1 | N92: 43223
B93: PARTICULARES | C93: ARANESP | D93: ARANESP 80MCG/0.4ML JGP CAJ C/1 | E93: 1-46672 | F93: 1131 | G93: 1131 | H93: FLORES Y REGALOS (CNBV) | I93: SIN INFORMACION | J93: TLALPAN | K93: SIN PROGRAMA | L93: VENTA | M93: 1 | N93: 43223
B94: PARTICULARES | C94: KYPROLIS | D94: KYPROLIS 60MG FAM CAJ C/1 | E94: 1-46600 | F94: 1117 | G94: 1117 | H94: STAR MEDICA (VERACRUZ) | I94: SIN INFORMACION | J94: VERACRUZ | K94: SIN PROGRAMA | L94: VENTA | M94: 1 | N94: 43223
B95: PARTICULARES | C95: NEULASTIM | D95: NEULASTIM 6 mg/0.6 ml JGP CAJ C/1 | E95: 1-45414 | F95: 37066 | G95: 37066 | H95: FAR COI CENTRO ONCOLOGICO INTERNACIONAL SA DE CV | I95: SIN INFORMACION | J95: GUADALAJARA 3 | K95: SIN PROGRAMA | L95: VENTA | M95: 2 | N95: 43223
B96: B Y A | C96: NEULASTIM | D96: NEULASTIM 6 mg/0.6 ml JGP CAJ C/1 | E96: 1-46560 | F96: 2474946 | G96: 868612 | H96: GARCIA LIZBETT VANESSA | I96: ONCOLOGIA | J96: BOSQUES | K96: SIN PROGRAMA | L96: VENTA | M96: 1 | N96: 43223
B97: PARTICULARES | C97: NEUPOGEN | D97: NEUPOGEN 300 mcg/0.5 ml 1 JGP C/0.5 ml | E97: 1-46257 | F97: 533 | G97: 533 | H97: OPERADORA DE HOSPITALES ANGELES ( CD JUAREZ ) | I97: SIN INFORMACION | J97: CD JUAREZ 3 | K97: SIN PROGRAMA | L97: VENTA | M97: 1 | N97: 43223
B98: MOSTRADOR | C98: NPLATE | D98: NPLATE 250 mcg FAM C/1 | E98: 1-45690 | F98: 2953067 | G98: 647422 | H98: LOPEZ JULIO CESAR | I98: MEDICINA INTERNA | J98: CD OBREGON | K98: SIN PROGRAMA | L98: VENTA | M98: 1 | N98: 43223
B99: PARTICULARES | C99: NPLATE | D99: NPLATE 250 mcg FAM C/1 | E99: 1-45227 | F99: 524 | G99: 524 | H99: OPERADORA DE HOSPITALES ANGELES (METROPOLITANO) | I99: SIN INFORMACION | J99: TLACOTALPAN | K99: SIN PROGRAMA | L99: VENTA | M99: 1 | N99: 43223
B100: PARTICULARES | C100: NPLATE | D100: NPLATE 250 mcg FAM C/1 | E100: 1-46429 | F100: 525 | G100: 525 | H100: OPERADORA DE HOSPITALES ANGELES (GINECO OBSTETRICA) | I100: SIN INFORMACION | J100: ESCANDON | K100: SIN PROGRAMA | L100: VENTA | M100: 1 | N100: 43223
B101: MOSTRADOR | C101: PROLIA | D101: PROLIA 60MG/1ML JPRELL CAJ C/1 | E101: 1-45765 | F101: 968092 | G101: 600306 | H101: MORGAN GILBERTO | I101: MEDICINA GENERAL | J101: GUADALAJARA 3 | K101: CON PROGRAMA | L101: VENTA | M101: 1 | N101: 43223
B102: MOSTRADOR | C102: PROLIA | D102: PROLIA 60MG/1ML JPRELL CAJ C/1 | E102: 1-45856 | F102: 967946 | G102: 635341 | H102: SIN INFORMACION | I102: SIN INFORMACION | J102: VILLA COAPA | K102: CON PROGRAMA | L102: VENTA | M102: 1 | N102: 43223
B103: MOSTRADOR | C103: PROLIA | D103: PROLIA 60MG/1ML JPRELL CAJ C/1 | E103: 1-46074 | F103: 2958095 | G103: 556064 | H103: MORALES RAMSES ALEJANDRO | I103: MEDICINA GENERAL | J103: GUADALAJARA 2 | K103: CON PROGRAMA | L103: VENTA | M103: 1 | N103: 43223
B104: MOSTRADOR | C104: PROLIA | D104: PROLIA 60MG/1ML JPRELL CAJ C/1 | E104: 1-46195 | F104: 1202730 | G104: 635341 | H104: SIN INFORMACION | I104: SIN INFORMACION | J104: MONTERREY 5 | K104: CON PROGRAMA | L104: VENTA | M104: 1 | N104: 43223
B105: MOSTRADOR | C105: PROLIA | D105: PROLIA 60MG/1ML JPRELL CAJ C/1 | E105: 1-46246 | F105: 2958146 | G105: 622903 | H105: HUERTA JOSE MIGUEL | I105: ORTOPEDIA Y TRAUMATOLOGIA | J105: GUADALAJARA 2 | K105: CON PROGRAMA | L105: VENTA | M105: 1 | N105: 43223
B106: MOSTRADOR | C106: PROLIA | D106: PROLIA 60MG/1ML JPRELL CAJ C/1 | E106: 1-46376 | F106: 2958211 | G106: 562740 | H106: BAEZA CAMACHO JOSE RAYMUNDO | I106: MEDICINA GENERAL | J106: GUADALAJARA 2 | K106: SIN PROGRAMA | L106: VENTA | M106: 1 | N106: 43223
B107: MOSTRADOR | C107: PROLIA | D107: PROLIA 60MG/1ML JPRELL CAJ C/1 | E107: 1-46545 | F107: 956462 | G107: 635341 | H107: SIN INFORMACION | I107: SIN INFORMACION | J107: CANCUN | K107: CON PROGRAMA | L107: VENTA | M107: 1 | N107: 43223
B108: MOSTRADOR | C108: PROLIA | D108: PROLIA 60MG/1ML JPRELL CAJ C/1 | E108: 1-46644 | F108: 1086596 | G108: 635341 | H108: SIN INFORMACION | I108: SIN INFORMACION | J108: CHIHUAHUA | K108: CON PROGRAMA | L108: VENTA | M108: 1 | N108: 43223
B109: MOSTRADOR | C109: PROLIA | D109: PROLIA 60MG/1ML JPRELL CAJ C/1 | E109: 1-46663 | F109: 826540 | G109: 593415 | H109: KIRSCH RAMOS ARMANDO | I109: SIN INFORMACION | J109: XALAPA | K109: CON PROGRAMA | L109: VENTA | M109: 1 | N109: 43223
B110: MOSTRADOR | C110: PROLIA | D110: PROLIA 60MG/1ML JPRELL CAJ C/1 | E110: 1-46777 | F110: 661052 | G110: 635341 | H110: SIN INFORMACION | I110: SIN INFORMACION | J110: MERIDA | K110: CON PROGRAMA | L110: VENTA | M110: 1 | N110: 43223
... B188: PARTICULARES | C188: ARANESP | D188: ARANESP 60MCG/0.3ML JPRELL CAJ C/4 | E188: 1-50768 | F188: 527 | G188: 527 | H188: OPERADORA DE HOSPITALES ANGELES (PUEBLA 3) | I188: SIN INFORMACION | J188: PUEBLA 3 | K188: SIN PROGRAMA | L188: VENTA | M188: 1 | N188: 43227
B189: B Y A | C189: ARANESP | D189: ARANESP 60MCG/0.3ML JPRELL CAJ C/4 | E189: 1-51238 | F189: 402736 | G189: 568104 | H189: ENRIQUEZ LUIS ENRIQUE | I189: MEDICINA GENERAL | J189: ESCANDON | K189: SIN PROGRAMA | L189: VENTA | M189: 1 | N189: 43227
B190: B Y A | C190: ARANESP | D190: ARANESP 60MCG/0.3ML JPRELL CAJ C/4 | E190: 1-51615 | F190: 402736 | G190: 568104 | H190: ENRIQUEZ LUIS ENRIQUE | I190: MEDICINA GENERAL | J190: ESCANDON | K190: SIN PROGRAMA | L190: VENTA | M190: 1 | N190: 43227
B191: PARTICULARES | C191: KYPROLIS | D191: KYPROLIS 60MG FAM CAJ C/1 | E191: 1-49889 | F191: 564 | G191: 564 | H191: PROMOTORA POBLANA | I191: SIN INFORMACION | J191: PUEBLA 3 | K191: SIN PROGRAMA | L191: VENTA | M191: 2 | N191: 43227
B192: PARTICULARES | C192: KYPROLIS | D192: KYPROLIS 60MG FAM CAJ C/1 | E192: 1-51649 | F192: 377 | G192: 377 | H192: HOSPITAL MEXICO AMERICANO | I192: SIN INFORMACION | J192: GUADALAJARA 3 | K192: SIN PROGRAMA | L192: VENTA | M192: 1 | N192: 43227
B193: MOSTRADOR | C193: NEUPOGEN | D193: NEUPOGEN 300 mcg/0.5 ml 1 JGP C/0.5 ml | E193: 1-51077 | F193: 2954327 | G193: 618874 | H193: MENDOZA RAQUEL | I193: MEDICINA GENERAL | J193: TOLUCA 2 | K193: SIN PROGRAMA | L193: VENTA | M193: 1 | N193: 43227
B194: MOSTRADOR | C194: NEUPOGEN | D194: NEUPOGEN 300 mcg/0.5 ml 1 JGP C/0.5 ml | E194: 1-50595 | F194: 2470446 | G194: 561802 | H194: CANO JORGE | I194: SIN INFORMACION | J194: PUEBLA 3 | K194: SIN PROGRAMA | L194: VENTA | M194: 7 | N194: 43227
B195: PARTICULARES | C195: NEUPOGEN | D195: NEUPOGEN 300 mcg/0.5 ml 1 JGP C/0.5 ml | E195: 1-49806 | F195: 214 | G195: 214 | H195: CHRISTUS MUGUERZA | I195: SIN INFORMACION | J195: PUEBLA 3 | K195: SIN PROGRAMA | L195: VENTA | M195: 1 | N195: 43227
B196: PARTICULARES | C196: NEUPOGEN | D196: NEUPOGEN 300 mcg/0.5 ml 1 JGP C/0.5 ml | E196: 1-49866 | F196: 564 | G196: 564 | H196: PROMOTORA POBLANA | I196: SIN INFORMACION | J196: PUEBLA 3 | K196: SIN PROGRAMA | L196: VENTA | M196: 3 | N196: 43227
B197: PARTICULARES | C197: NEUPOGEN | D197: NEUPOGEN 300 mcg/0.5 ml 1 JGP C/0.5 ml | E197: 1-49935 | F197: 522 | G197: 522 | H197: OPERADORA DE HOSPITALES ANGELES (PEDREGAL) | I197: SIN INFORMACION | J197: TLALPAN | K197: SIN PROGRAMA | L197: VENTA | M197: 18 | N197: 43227
B198: PARTICULARES | C198: NEUPOGEN | D198: NEUPOGEN 300 mcg/0.5 ml 1 JGP C/0.5 ml | E198: 1-50011 | F198: 524 | G198: 524 | H198: OPERADORA DE HOSPITALES ANGELES (METROPOLITANO) | I198: SIN INFORMACION | J198: TLACOTALPAN | K198: SIN PROGRAMA | L198: VENTA | M198: 6 | N198: 43227
B199: PARTICULARES | C199: NEUPOGEN | D199: NEUPOGEN 300 mcg/0.5 ml 1 JGP C/0.5 ml | E199: 1-50053 | F199: 526 | G199: 526 | H199: OPERADORA DE HOSPITALES ANGELES (MOCEL) | I199: SIN INFORMACION | J199: TLACOTALPAN | K199: SIN PROGRAMA | L199: VENTA | M199: 3 | N199: 43227
B200: PARTICULARES | C200: NEUPOGEN | D200: NEUPOGEN 300 mcg/0.5 ml 1 JGP C/0.5 ml | E200: 1-50130 | F200: 537 | G200: 537 | H200: OPERADORA DE HOSPITALES ANGELES (ACOXPA) | I200: SIN INFORMACION | J200: TLALPAN | K200: SIN PROGRAMA | L200: VENTA | M200: 7 | N200: 43227
B201: PARTICULARES | C201: NEUPOGEN | D201: NEUPOGEN 300 mcg/0.5 ml 1 JGP C/0.5 ml | E201: 1-50218 | F201: 525 | G201: 525 | H201: OPERADORA DE HOSPITALES ANGELES (GINECO OBSTETRICA) | I201: SIN INFORMACION | J201: ESCANDON | K201: SIN PROGRAMA | L201: VENTA | M201: 8 | N201: 43227
B202: PARTICULARES | C202: NEUPOGEN | D202: NEUPOGEN 300 mcg/0.5 ml 1 JGP C/0.5 ml | E202: 1-50293 | F202: 521 | G202: 521 | H202: OPERADORA DE HOSPITALES ANGELES (SANTA ELENA) | I202: SIN INFORMACION | J202: ROMA NORTE | K202: SIN PROGRAMA | L202: VENTA | M202: 2 | N202: 43227
... B245: B Y A | C245: REPATHA | D245: REPATHA 140MG/ML PLP CAJ C/1 | E245: 1-50397 | F245: 1110250 | G245: 574017 | H245: JALON CONSTANTE HECTOR ALFREDO | I245: MEDICINA GENERAL | J245: PRADO NORTE | K245: SIN PROGRAMA | L245: VENTA | M245: 2 | N245: 43227
B246: B Y A | C246: REPATHA | D246: REPATHA 140MG/ML PLP CAJ C/1 | E246: 1-51615 | F246: 402736 | G246: 568104 | H246: ENRIQUEZ LUIS ENRIQUE | I246: MEDICINA GENERAL | J246: ESCANDON | K246: SIN PROGRAMA | L246: VENTA | M246: 6 | N246: 43227
B247: MOSTRADOR | C247: XGEVA | D247: XGEVA 120MG/1.7ML F A CAJ C/1 | E247: 1-50187 | F247: 856328 | G247: 2944979 | H247: RODRIGUEZ JORGE | I247: SIN INFORMACION | J247: VILLAHERMOSA 2 | K247: SIN PROGRAMA | L247: VENTA | M247: 1 | N247: 43227
B248: PARTICULARES | C248: XGEVA | D248: XGEVA 120MG/1.7ML F A CAJ C/1 | E248: 1-50768 | F248: 527 | G248: 527 | H248: OPERADORA DE HOSPITALES ANGELES (PUEBLA 3) | I248: SIN INFORMACION | J248: PUEBLA 3 | K248: SIN PROGRAMA | L248: VENTA | M248: 3 | N248: 43227
B249: PARTICULARES | C249: XGEVA | D249: XGEVA 120MG/1.7ML F A CAJ C/1 | E249: 1-51417 | F249: 1006 | G249: 1006 | H249: OPERADORA DE HOSPITALES ANGELES MONTERREY | I249: SIN INFORMACION | J249: MONTERREY 5 | K249: SIN PROGRAMA | L249: VENTA | M249: 1 | N249: 43227
B250: B Y A | C250: XGEVA | D250: XGEVA 120MG/1.7ML F A CAJ C/1 | E250: 1-51496 | F250: 2464727 | G250: 603452 | H250: ARRIETA RODRIGUEZ OSCAR GERARDO | I250: MEDICINA GENERAL | J250: CUERNAVACA | K250: SIN PROGRAMA | L250: VENTA | M250: 1 | N250: 43227
B251: PARTICULARES | C251: ARANESP | D251: ARANESP 40MCG/0.4ML JPRELL CAJ C/4 | E251: 1-51920 | F251: 48 | G251: 48 | H251: HOSPITAL ABC OBSERVATORIO | I251: SIN INFORMACION | J251: ROMA NORTE | K251: SIN PROGRAMA | L251: VENTA | M251: 2 | N251: 43228
B252: MOSTRADOR | C252: ARANESP | D252: ARANESP 500MCG/1ML JPRELL CAJ C/1 | E252: 1-51831 | F252: 792914 | G252: 651389 | H252: LOPEZ MARIA OLIMPIA | I252: SIN INFORMACION | J252: TLALPAN 2 | K252: SIN PROGRAMA | L252: VENTA | M252: 1 | N252: 43228
B253: PARTICULARES | C253: ARANESP | D253: ARANESP 500MCG/1ML JPRELL CAJ C/1 | E253: 1-52856 | F253: 531 | G253: 531 | H253: OPERADORA DE HOSPITALES ANGELES (GDL 1 Y 2) | I253: SIN INFORMACION | J253: GUADALAJARA 3 | K253: SIN PROGRAMA | L253: VENTA | M253: 1 | N253: 43228
B254: PARTICULARES | C254: ARANESP | D254: ARANESP 500MCG/1ML JPRELL CAJ C/1 | E254: 1-53182 | F254: 37066 | G254: 37066 | H254: FAR COI CENTRO ONCOLOGICO INTERNACIONAL SA DE CV | I254: SIN INFORMACION | J254: GUADALAJARA 3 | K254: SIN PROGRAMA | L254: VENTA | M254: 1 | N254: 43228
B255: B Y A | C255: ARANESP | D255: ARANESP 500MCG/1ML JPRELL CAJ C/1 | E255: 1-52607 | F255: 2458689 | G255: 604302 | H255: REYES JESSICA GRICELDA | I255: MEDICINA GENERAL | J255: SAN LUIS POTOSI | K255: SIN PROGRAMA | L255: VENTA | M255: 1 | N255: 43228
B256: MOSTRADOR | C256: ARANESP | D256: ARANESP 60MCG/0.3ML JPRELL CAJ C/4 | E256: 1-53506 | F256: 2961889 | G256: 588319 | H256: VALDES CEPEDA ALEJANDRO | I256: MEDICINA GENERAL | J256: MONTERREY 5 | K256: SIN PROGRAMA | L256: VENTA | M256: 1 | N256: 43228
B257: PARTICULARES | C257: ARANESP | D257: ARANESP 60MCG/0.3ML JPRELL CAJ C/4 | E257: 1-52578 | F257: 537 | G257: 537 | H257: OPERADORA DE HOSPITALES ANGELES (ACOXPA) | I257: SIN INFORMACION | J257: TLALPAN | K257: SIN PROGRAMA | L257: VENTA | M257: 1 | N257: 43228
B258: B Y A | C258: ARANESP | D258: ARANESP 60MCG/0.3ML JPRELL CAJ C/4 | E258: 1-53347 | F258: 1175846 | G258: 565376 | H258: CATANEO DAVILA ANTONIO ENRIQUE | I258: MEDICINA GENERAL | J258: SANATORIO DURANGO | K258: SIN PROGRAMA | L258: VENTA | M258: 1 | N258: 43228
... B283: B Y A | C283: PROLIA | D283: PROLIA 60MG/1ML JPRELL CAJ C/1 | E283: 1-52327 | F283: 2961310 | G283: 646179 | H283: AGUILAR GUADALUPE CECILIA | I283: MEDICINA GENERAL | J283: PUEBLA | K283: SIN PROGRAMA | L283: VENTA | M283: 1 | N283: 43228
...

Sheet Adherencia Mimpara
B2: ADHERENCIA MIMPARA
B3: ENERO 11 - MAYO 2018
B6: CLAVE PX | C6: MES | D6: 40544 | E6: 40575 | F6: 40603 | G6: 40634 | H6: 40664 | I6: 40695 | J6: 40725 | K6: 40756 | L6: 40787 | M6: 40817 | N6: 40848 | O6: 40878 | P6: 40909 | Q6: 40940 | R6: 40969 | S6: 41000 | T6: 41030 | U6: 41061 | V6: 41091 | W6: 41122 | X6: 41153 | Y6: 41183 | Z6: 41214 | AA6: 41244 | AB6: 41275 | AC6: 41306 | AD6: 41334 | AE6: 41365 | AF6: 41395 | AG6: 41426 | AH6: 41456 | AI6: 41487 | AJ6: 41518 | AK6: 41548 | AL6: 41579 | AM6: 41609 | AN6: 41640 | AO6: 41671 | AP6: 41699 | AQ6: 41730 | AR6: 41760 | AS6: 41791 | AT6: 41821 | AU6: 41852 | AV6: 41883 | AW6: 41913 | AX6: 41944 | AY6: 41974 | AZ6: 42005 | BA6: 42036 | BB6: 42064 | BC6: 42095 | BD6: 42125 | BE6: 42156 | BF6: 42186 | BG6: 42217 | BH6: 42248 | BI6: 42278 | BJ6: 42309 | BK6: 42339 | BL6: 42370 | BM6: 42401 | BN6: 42430 | BO6: 42461 | BP6: 42491 | BQ6: 42522 | BR6: 42552 | BS6: 42583 | BT6: 42614 | BU6: 42644 | BV6: 42675 | BW6: 42705 | BX6: 42736 | BY6: 42767 | BZ6: 42795 | CA6: 42826 | CB6: 42856 | CC6: 42887 | CD6: 42917 | CE6: 42948 | CF6: 42979 | CG6: 43009 | CH6: 43040 | CI6: 43070 | CJ6: 43101 | CK6: 43132 | CL6: 43160 | CM6: 43191 | CN6: 43221 | CO6: 43252 | CP6: 43282 | CQ6: 43313 | CR6: 43344 | CS6: 43374 | CT6: 43405 | CU6: 43435 | CV6: Total general
B7: 32777 | C7: 40544 | D7: 3 | F7: 10 | Q7: 5 | V7: 8 | AD7: 5 | AL7: 3 | AN7: 3 | AS7: 2 | CV7: =SUM(D7:CU7) -> 39
B8: 284984 | C8: 40544 | D8: 2 | CV8: =SUM(D8:CU8) -> 2
B9: 208529 | C9: 40544 | D9: 1 | F9: 2 | G9: 2 | H9: 3 | I9: 1 | J9: 1 | K9: 2 | L9: 1 | M9: 5 | O9: 2 | P9: 2 | Q9: 2 | CV9: =SUM(D9:CU9) -> 24
B10: 285841 | C10: 40544 | D10: 1 | F10: 1 | H10: 1 | J10: 1 | K10: 1 | L10: 1 | X10: 1 | Y10: 1 | AA10: 1 | AC10: 1 | CV10: =SUM(D10:CU10) -> 10
B11: 282690 | C11: 40544 | D11: 1 | CV11: =SUM(D11:CU11) -> 1
C12: Total general | D12: =COUNT(D7:D11) -> 5 | E12: =COUNT(E7:E11) -> 0 | F12: =COUNT(F7:F11) -> 3 | G12: =COUNT(G7:G11) -> 1 | H12: =COUNT(H7:H11) -> 2 | I12: =COUNT(I7:I11) -> 1 | J12: =COUNT(J7:J11) -> 2 | K12: =COUNT(K7:K11) -> 2 | ... CU12: =COUNT(CU7:CU11) -> 0 | CV12: =SUM(CV7:CV11) -> 76
B14: CLAVE PX | C14: MES | D14: 40544 | E14: 40575 | F14: 40603 | G14: 40634 | H14: 40664 | I14: 40695 | J14: 40725 | K14: 40756 | L14: 40787 | M14: 40817 | N14: 40848 | O14: 40878 | P14: 40909 | Q14: 40940 | R14: 40969 | S14: 41000 | T14: 41030 | U14: 41061 | V14: 41091 | W14: 41122 | X14: 41153 | Y14: 41183 | Z14: 41214 | AA14: 41244 | AB14: 41275 | AC14: 41306 | AD14: 41334 | AE14: 41365 | AF14: 41395 | AG14: 41426 | AH14: 41456 | AI14: 41487 | AJ14: 41518 | AK14: 41548 | AL14: 41579 | AM14: 41609 | AN14: 41640 | AO14: 41671 | AP14: 41699 | AQ14: 41730 | AR14: 41760 | AS14: 41791 | AT14: 41821 | AU14: 41852 | AV14: 41883 | AW14: 41913 | AX14: 41944 | AY14: 41974 | AZ14: 42005 | BA14: 42036 | BB14: 42064 | BC14: 42095 | BD14: 42125 | BE14: 42156 | BF14: 42186 | BG14: 42217 | BH14: 42248 | BI14: 42278 | BJ14: 42309 | BK14: 42339 | BL14: 42370 | BM14: 42401 | BN14: 42430 | BO14: 42461 | BP14: 42491 | BQ14: 42522 | BR14: 42552 | BS14: 42583 | BT14: 42614 | BU14: 42644 | BV14: 42675 | BW14: 42705 | BX14: 42736 | BY14: 42767 | BZ14: 42795 | CA14: 42826 | CB14: 42856 | CC14: 42887 | CD14: 42917 | CE14: 42948 | CF14: 42979 | CG14: 43009 | CH14: 43040 | CI14: 43070 | CJ14: 43101 | CK14: 43132 | CL14: 43160 | CM14: 43191 | CN14: 43221 | CO14: 43252 | CP14: 43282 | CQ14: 43313 | CR14: 43344 | CS14: 43374 | CT14: 43405 | CU14: 43435 | CV14: Total general
B15: 230143 | C15: 40575 | E15: 2 | H15: 1 | CV15: =SUM(D15:CU15) -> 3
B16: 258057 | C16: 40575 | E16: 2 | CV16: =SUM(D16:CU16) -> 2
B17: 287221 | C17: 40575 | E17: 2 | CV17: =SUM(D17:CU17) -> 2
B18: 287440 | C18: 40575 | E18: 2 | CV18: =SUM(D18:CU18) -> 2
B19: 287108 | C19: 40575 | E19: 1 | F19: 2 | G19: 1 | H19: 1 | I19: 1 | J19: 2 | Q19: 1 | CV19: =SUM(D19:CU19) -> 9
B20: 221607 | C20: 40575 | E20: 1 | F20: 2 | CV20: =SUM(D20:CU20) -> 3
B21: 289632 | C21: 40575 | E21: 1 | F21: 1 | G21: 2 | H21: 1 | CV21: =SUM(D21:CU21) -> 5
B22: 289524 | C22: 40575 | E22: 1 | F22: 1 | G22: 1 | H22: 2 | I22: 1 | J22: 1 | U22: 1 | W22: 1 | CV22: =SUM(D22:CU22) -> 9
B23: 237488 | C23: 40575 | E23: 1 | F23: 1 | G23: 1 | H23: 1 | J23: 1 | CV23: =SUM(D23:CU23) -> 5
B24: 286281 | C24: 40575 | E24: 1 | F24: 1 | CV24: =SUM(D24:CU24) -> 2
B25: 286417 | C25: 40575 | E25: 1 | F25: 1 | CV25: =SUM(D25:CU25) -> 2
B26: 287782 | C26: 40575 | E26: 1 | F26: 1 | CV26: =SUM(D26:CU26) -> 2
B27: 188585 | C27: 40575 | E27: 1 | G27: 1 | I27: 1 | J27: 1 | K27: 1 | L27: 1 | M27: 1 | N27: 1 | P27: 1 | Q27: 1 | R27: 1 | S27: 1 | T27: 1 | CV27: =SUM(D27:CU27) -> 13
B28: 105961 | C28: 40575 | E28: 1 | G28: 1 | CV28: =SUM(D28:CU28) -> 2
B29: 287514 | C29: 40575 | E29: 1 | G29: 1 | CV29: =SUM(D29:CU29) -> 2
B30: 287993 | C30: 40575 | E30: 1 | G30: 1 | AG30: 3 | AI30: 3 | AK30: 3 | CV30: =SUM(D30:CU30) -> 11
B31: 170977 | C31: 40575 | E31: 1 | I31: 1 | K31: 1 | L31: 1 | M31: 1 | Q31: 1 | CV31: =SUM(D31:CU31) -> 6
B32: 286333 | C32: 40575 | E32: 1 | I32: 1 | J32: 1 | P32: 1 | AC32: 0 | CV32: =SUM(D32:CU32) -> 4
B33: 31832 | C33: 40575 | E33: 1 | CV33: =SUM(D33:CU33) -> 1
B34: 176610 | C34: 40575 | E34: 1 | J34: 1 | M34: 1 | N34: 1 | P34: 1 | CV34: =SUM(D34:CU34) -> 5
B35: 264116 | C35: 40575 | E35: 1 | CV35: =SUM(D35:CU35) -> 1
B36: 286044 | C36: 40575 | E36: 1 | CV36: =SUM(D36:CU36) -> 1
B37: 286238 | C37: 40575 | E37: 1 | CV37: =SUM(D37:CU37) -> 1
B38: 286243 | C38: 40575 | E38: 1 | CV38: =SUM(D38:CU38) -> 1
B39: 287428 | C39: 40575 | E39: 1 | CV39: =SUM(D39:CU39) -> 1
B40: 289685 | C40: 40575 | E40: 1 | CV40: =SUM(D40:CU40) -> 1
C41: Total general | E41: =COUNT(E15:E40) -> 26 | F41: =COUNT(F15:F40) -> 8 | G41: =COUNT(G15:G40) -> 8 | H41: =COUNT(H15:H40) -> 5 | I41: =COUNT(I15:I40) -> 5 | J41: =COUNT(J15:J40) -> 6 | K41: =COUNT(K15:K40) -> 2 | L41: =COUNT(L15:L40) -> 2 | ... CU41: =COUNT(CU15:CU40) -> 0 | CV41: =SUM(CV15:CV40) -> 96
B43: CLAVE PX | C43: MES | D43: 40544 | E43: 40575 | F43: 40603 | G43: 40634 | H43: 40664 | I43: 40695 | J43: 40725 | K43: 40756 | L43: 40787 | M43: 40817 | N43: 40848 | O43: 40878 | P43: 40909 | Q43: 40940 | R43: 40969 | S43: 41000 | T43: 41030 | U43: 41061 | V43: 41091 | W43: 41122 | X43: 41153 | Y43: 41183 | Z43: 41214 | AA43: 41244 | AB43: 41275 | AC43: 41306 | AD43: 41334 | AE43: 41365 | AF43: 41395 | AG43: 41426 | AH43: 41456 | AI43: 41487 | AJ43: 41518 | AK43: 41548 | AL43: 41579 | AM43: 41609 | AN43: 41640 | AO43: 41671 | AP43: 41699 | AQ43: 41730 | AR43: 41760 | AS43: 41791 | AT43: 41821 | AU43: 41852 | AV43: 41883 | AW43: 41913 | AX43: 41944 | AY43: 41974 | AZ43: 42005 | BA43: 42036 | BB43: 42064 | BC43: 42095 | BD43: 42125 | BE43: 42156 | BF43: 42186 | BG43: 42217 | BH43: 42248 | BI43: 42278 | BJ43: 42309 | BK43: 42339 | BL43: 42370 | BM43: 42401 | BN43: 42430 | BO43: 42461 | BP43: 42491 | BQ43: 42522 | BR43: 42552 | BS43: 42583 | BT43: 42614 | BU43: 42644 | BV43: 42675 | BW43: 42705 | BX43: 42736 | BY43: 42767 | BZ43: 42795 | CA43: 42826 | CB43: 42856 | CC43: 42887 | CD43: 42917 | CE43: 42948 | CF43: 42979 | CG43: 43009 | CH43: 43040 | CI43: 43070 | CJ43: 43101 | CK43: 43132 | CL43: 43160 | CM43: 43191 | CN43: 43221 | CO43: 43252 | CP43: 43282 | CQ43: 43313 | CR43: 43344 | CS43: 43374 | CT43: 43405 | CU43: 43435 | CV43: Total general
B44: 10413 | C44: 40603 | F44: 3 | H44: 3 | M44: 1 | N44: 3 | P44: 2 | W44: 2 | AA44: 12 | CV44: =SUM(D44:CU44) -> 26
B45: 201347 | C45: 40603 | F45: 2 | G45: 1 | H45: 4 | I45: 2 | T45: 2 | AE45: 1 | CV45: =SUM(D45:CU45) -> 12
B46: 291357 | C46: 40603 | F46: 2 | G46: 1 | H46: 1 | I46: 1 | J46: 1 | K46: 1 | L46: 1 | M46: 1 | CV46: =SUM(D46:CU46) -> 9
B47: 294130 | C47: 40603 | F47: 2 | I47: 2 | L47: 1 | M47: 2 | O47: 1 | CV47: =SUM(D47:CU47) -> 8
B48: 291621 | C48: 40603 | F48: 2 | I48: 1 | CV48: =SUM(D48:CU48) -> 3
B49: 224105 | C49: 40603 | F49: 2 | CV49: =SUM(D49:CU49) -> 2
B50: 293075 | C50: 40603 | F50: 1 | G50: 2 | H50: 3 | I50: 2 | J50: 2 | K50: 1 | L50: 2 | M50: 3 | N50: 1 | CV50: =SUM(D50:CU50) -> 17
B51: 291051 | C51: 40603 | F51: 1 | G51: 1 | H51: 1 | I51: 1 | K51: 1 | N51: 1 | O51: 1 | Q51: 1 | R51: 1 | Y51: 1 | AB51: 1 | CV51: =SUM(D51:CU51) -> 11
B52: 257718 | C52: 40603 | F52: 1 | G52: 1 | H52: 1 | J52: 1 | K52: 2 | L52: 1 | M52: 1 | P52: 1 | CV52: =SUM(D52:CU52) -> 9
B53: 291766 | C53: 40603 | F53: 1 | G53: 1 | H53: 1 | CV53: =SUM(D53:CU53) -> 3
B54: 293448 | C54: 40603 | F54: 1 | G54: 1 | H54: 1 | CV54: =SUM(D54:CU54) -> 3
B55: 291479 | C55: 40603 | F55: 1 | G55: 1 | CV55: =SUM(D55:CU55) -> 2
B56: 292553 | C56: 40603 | F56: 1 | H56: 1 | I56: 1 | J56: 1 | K56: 1 | L56: 2 | M56: 1 | N56: 1 | O56: 1 | P56: 1 | Q56: 2 | R56: 2 | S56: 2 | U56: 2 | V56: 1 | W56: 2 | Y56: 1 | Z56: 2 | AA56: 2 | AB56: 1 | AC56: 1 | AD56: 2 | AE56: 1 | AF56: 1 | AG56: 1 | AH56: 1 | AI56: 1 | AJ56: 1 | AK56: 1 | AL56: 1 | AM56: 1 | AN56: 1 | AO56: 1 | AP56: 2 | AQ56: 1 | CV56: =SUM(D56:CU56) -> 45
B57: 31267 | C57: 40603 | F57: 1 | AE57: 2 | CV57: =SUM(D57:CU57) -> 3
B58: 142520 | C58: 40603 | F58: 1 | J58: 2 | CV58: =SUM(D58:CU58) -> 3
B59: 201417 | C59: 40603 | F59: 1 | CV59: =SUM(D59:CU59) -> 1
B60: 272057 | C60: 40603 | F60: 1 | CV60: =SUM(D60:CU60) -> 1
B61: 282464 | C61: 40603 | F61: 1 | J61: 2 | CV61: =SUM(D61:CU61) -> 3
B62: 289801 | C62: 40603 | F62: 1 | CV62: =SUM(D62:CU62) -> 1
B63: 290043 | C63: 40603 | F63: 1 | CV63: =SUM(D63:CU63) -> 1
B64: 291264 | C64: 40603 | F64: 1 | CV64: =SUM(D64:CU64) -> 1
B65: 291306 | C65: 40603 | F65: 1 | CV65: =SUM(D65:CU65) -> 1
B66: 291377 | C66: 40603 | F66: 1 | CV66: =SUM(D66:CU66) -> 1
B67: 291406 | C67: 40603 | F67: 1 | N67: 1 | CV67: =SUM(D67:CU67) -> 2
B68: 291456 | C68: 40603 | F68: 1 | CV68: =SUM(D68:CU68) -> 1
B69: 291895 | C69: 40603 | F69: 1 | X69: 1 | AA69: 1 | CV69: =SUM(D69:CU69) -> 3
B70: 293992 | C70: 40603 | F70: 1 | CV70: =SUM(D70:CU70) -> 1
C71: Total general | F71: =COUNT(F44:F70) -> 27 | G71: =COUNT(G44:G70) -> 8 | H71: =COUNT(H44:H70) -> 9 | I71: =COUNT(I44:I70) -> 7 | J71: =COUNT(J44:J70) -> 6 | K71: =COUNT(K44:K70) -> 5 | L71: =COUNT(L44:L70) -> 5 | M71: =COUNT(M44:M70) -> 6 | ... CU71: =COUNT(CU44:CU70) -> 0 | CV71: =SUM(CV44:CV70) -> 173
B73: CLAVE PX | C73: MES | D73: 40544 | E73: 40575 | F73: 40603 | G73: 40634 | H73: 40664 | I73: 40695 | J73: 40725 | K73: 40756 | L73: 40787 | M73: 40817 | N73: 40848 | O73: 40878 | P73: 40909 | Q73: 40940 | R73: 40969 | S73: 41000 | T73: 41030 | U73: 41061 | V73: 41091 | W73: 41122 | X73: 41153 | Y73: 41183 | Z73: 41214 | AA73: 41244 | AB73: 41275 | AC73: 41306 | AD73: 41334 | AE73: 41365 | AF73: 41395 | AG73: 41426 | AH73: 41456 | AI73: 41487 | AJ73: 41518 | AK73: 41548 | AL73: 41579 | AM73: 41609 | AN73: 41640 | AO73: 41671 | AP73: 41699 | AQ73: 41730 | AR73: 41760 | AS73: 41791 | AT73: 41821 | AU73: 41852 | AV73: 41883 | AW73: 41913 | AX73: 41944 | AY73: 41974 | AZ73: 42005 | BA73: 42036 | BB73: 42064 | BC73: 42095 | BD73: 42125 | BE73: 42156 | BF73: 42186 | BG73: 42217 | BH73: 42248 | BI73: 42278 | BJ73: 42309 | BK73: 42339 | BL73: 42370 | BM73: 42401 | BN73: 42430 | BO73: 42461 | BP73: 42491 | BQ73: 42522 | BR73: 42552 | BS73: 42583 | BT73: 42614 | BU73: 42644 | BV73: 42675 | BW73: 42705 | BX73: 42736 | BY73: 42767 | BZ73: 42795 | CA73: 42826 | CB73: 42856 | CC73: 42887 | CD73: 42917 | CE73: 42948 | CF73: 42979 | CG73: 43009 | CH73: 43040 | CI73: 43070 | CJ73: 43101 | CK73: 43132 | CL73: 43160 | CM73: 43191 | CN73: 43221 | CO73: 43252 | CP73: 43282 | CQ73: 43313 | CR73: 43344 | CS73: 43374 | CT73: 43405 | CU73: 43435 | CV73: Total general
B74: 295423 | C74: 40634 | G74: 1 | H74: 1 | I74: 2 | K74: 1 | L74: 1 | N74: 1 | O74: 1 | Q74: 1 | U74: 1 | AA74: 1 | AF74: 1 | AH74: 1 | AQ74: 1 | CV74: =SUM(D74:CU74) -> 14
B75: 58942 | C75: 40634 | G75: 1 | H75: 1 | I75: 1 | J75: 1 | L75: 2 | O75: 1 | R75: 1 | AL75: 2 | CV75: =SUM(D75:CU75) -> 10
B76: 294811 | C76: 40634 | G76: 1 | H76: 1 | CV76: =SUM(D76:CU76) -> 2
B77: 295504 | C77: 40634 | G77: 1 | H77: 1 | V77: 0 | CV77: =SUM(D77:CU77) -> 2
B78: 295915 | C78: 40634 | G78: 1 | H78: 1 | V78: 1 | CV78: =SUM(D78:CU78) -> 3
B79: 294585 | C79: 40634 | G79: 1 | I79: 1 | O79: 1 | P79: 1 | CV79: =SUM(D79:CU79) -> 4
B80: 295779 | C80: 40634 | G80: 1 | I80: 1 | L80: 1 | P80: 1 | CV80: =SUM(D80:CU80) -> 4
B81: 100268 | C81: 40634 | G81: 1 | CV81: =SUM(D81:CU81) -> 1
B82: 211243 | C82: 40634 | G82: 1 | AT82: 4 | AY82: 2 | BB82: 3 | BQ82: 1 | BR82: 6 | BW82: 9 | CV82: =SUM(D82:CU82) -> 26
B83: 221506 | C83: 40634 | G83: 1 | CV83: =SUM(D83:CU83) -> 1
B84: 230785 | C84: 40634 | G84: 1 | CV84: =SUM(D84:CU84) -> 1
B85: 294652 | C85: 40634 | G85: 1 | CV85: =SUM(D85:CU85) -> 1
B86: 294770 | C86: 40634 | G86: 1 | CV86: =SUM(D86:CU86) -> 1
B87: 294803 | C87: 40634 | G87: 1 | CV87: =SUM(D87:CU87) -> 1
B88: 295564 | C88: 40634 | G88: 1 | CV88: =SUM(D88:CU88) -> 1
B89: 296028 | C89: 40634 | G89: 1 | CV89: =SUM(D89:CU89) -> 1
B90: 296192 | C90: 40634 | G90: 1 | CV90: =SUM(D90:CU90) -> 1
B91: 297208 | C91: 40634 | G91: 1 | CV91: =SUM(D91:CU91) -> 1
B92: 298341 | C92: 40634 | G92: 1 | L92: 1 | N92: 1 | P92: 1 | CV92: =SUM(D92:CU92) -> 4
C93: Total general | G93: =COUNT(G74:G92) -> 19 | H93: =COUNT(H74:H92) -> 5 | I93: =COUNT(I74:I92) -> 4 | J93: =COUNT(J74:J92) -> 1 | K93: =COUNT(K74:K92) -> 1 | L93: =COUNT(L74:L92) -> 4 | M93: =COUNT(M74:M92) -> 0 | N93: =COUNT(N74:N92) -> 2 | ... CU93: =COUNT(CU74:CU92) -> 0 | CV93: =SUM(CV74:CV92) -> 79
B95: CLAVE PX | C95: MES | D95: 40544 | E95: 40575 | F95: 40603 | G95: 40634 | H95: 40664 | I95: 40695 | J95: 40725 | K95: 40756 | L95: 40787 | M95: 40817 | N95: 40848 | O95: 40878 | P95: 40909 | Q95: 40940 | R95: 40969 | S95: 41000 | T95: 41030 | U95: 41061 | V95: 41091 | W95: 41122 | X95: 41153 | Y95: 41183 | Z95: 41214 | AA95: 41244 | AB95: 41275 | AC95: 41306 | AD95: 41334 | AE95: 41365 | AF95: 41395 | AG95: 41426 | AH95: 41456 | AI95: 41487 | AJ95: 41518 | AK95: 41548 | AL95: 41579 | AM95: 41609 | AN95: 41640 | AO95: 41671 | AP95: 41699 | AQ95: 41730 | AR95: 41760 | AS95: 41791 | AT95: 41821 | AU95: 41852 | AV95: 41883 | AW95: 41913 | AX95: 41944 | AY95: 41974 | AZ95: 42005 | BA95: 42036 | BB95: 42064 | BC95: 42095 | BD95: 42125 | BE95: 42156 | BF95: 42186 | BG95: 42217 | BH95: 42248 | BI95: 42278 | BJ95: 42309 | BK95: 42339 | BL95: 42370 | BM95: 42401 | BN95: 42430 | BO95: 42461 | BP95: 42491 | BQ95: 42522 | BR95: 42552 | BS95: 42583 | BT95: 42614 | BU95: 42644 | BV95: 42675 | BW95: 42705 | BX95: 42736 | BY95: 42767 | BZ95: 42795 | CA95: 42826 | CB95: 42856 | CC95: 42887 | CD95: 42917 | CE95: 42948 | CF95: 42979 | CG95: 43009 | CH95: 43040 | CI95: 43070 | CJ95: 43101 | CK95: 43132 | CL95: 43160 | CM95: 43191 | CN95: 43221 | CO95: 43252 | CP95: 43282 | CQ95: 43313 | CR95: 43344 | CS95: 43374 | CT95: 43405 | CU95: 43435 | CV95: Total general
B96: 60578 | C96: 40664 | H96: 2 | J96: 1 | K96: 1 | L96: 1 | R96: 2 | CV96: =SUM(D96:CU96) -> 7
B97: 283310 | C97: 40664 | H97: 1 | I97: 4 | J97: 3 | M97: 1 | N97: 1 | O97: 1 | P97: 2 | R97: 1 | T97: 1 | CV97: =SUM(D97:CU97) -> 15
B98: 299642 | C98: 40664 | H98: 1 | I98: 3 | J98: 1 | AF98: 1 | CV98: =SUM(D98:CU98) -> 6
B99: 174309 | C99: 40664 | H99: 1 | I99: 1 | J99: 1 | K99: 1 | L99: 2 | N99: 1 | O99: 1 | R99: 1 | S99: 2 | U99: 2 | V99: 2 | W99: 3 | Y99: 1 | Z99: 2 | AA99: 3 | AB99: 1 | AC99: 3 | AD99: 2 | AG99: 3 | AO99: 2 | AP99: 2 | BN99: 2 | CV99: =SUM(D99:CU99) -> 39
B100: 300159 | C100: 40664 | H100: 1 | I100: 1 | J100: 1 | Y100: 1 | CV100: =SUM(D100:CU100) -> 4
B101: 301509 | C101: 40664 | H101: 1 | I101: 1 | K101: 1 | CV101: =SUM(D101:CU101) -> 3
B102: 302205 | C102: 40664 | H102: 1 | I102: 1 | J102: 1 | M102: 1 | P102: 2 | CV102: =SUM(D102:CU102) -> 6
B103: 302741 | C103: 40664 | H103: 1 | I103: 1 | CV103: =SUM(D103:CU103) -> 2
B104: 173838 | C104: 40664 | H104: 1 | CV104: =SUM(D104:CU104) -> 1
B105: 186763 | C105: 40664 | H105: 1 | CV105: =SUM(D105:CU105) -> 1
B106: 273798 | C106: 40664 | H106: 1 | J106: 1 | L106: 1 | O106: 1 | CV106: =SUM(D106:CU106) -> 4
B107: 294739 | C107: 40664 | H107: 1 | CV107: =SUM(D107:CU107) -> 1
...

Sheet Seguimiento Mimpara
B2: MIMPARA
B3: ='Adherencia Mimpara'!B3 -> ENERO 11 - MAYO 2018
B6: PACIENTES NUEVOS Y ADHERENTES POR MES | CP6: RESUMEN
C7: 40544 | D7: 40575 | E7: 40603 | F7: 40634 | G7: 40664 | H7: 40695 | I7: 40725 | J7: 40756 | K7: 40787 | L7: 40817 | M7: 40848 | N7: 40878 | O7: 40909 | P7: 40940 | Q7: 40969 | R7: 41000 | S7: 41030 | T7: 41061 | U7: 41091 | V7: 41122 | W7: 41153 | X7: 41183 | Y7: 41214 | Z7: 41244 | AA7: 41275 | AB7: 41306 | AC7: 41334 | AD7: 41365 | AE7: 41395 | AF7: 41426 | AG7: 41456 | AH7: 41487 | AI7: 41518 | AJ7: 41548 | AK7: 41579 | AL7: 41609 | AM7: 41640 | AN7: 41671 | AO7: 41699 | AP7: 41730 | AQ7: 41760 | AR7: 41791 | AS7: 41821 | AT7: 41852 | AU7: 41883 | AV7: 41913 | AW7: 41944 | AX7: 41974 | AY7: 42005 | AZ7: 42036 | BA7: 42064 | BB7: 42095 | BC7: 42125 | BD7: 42156 | BE7: 42186 | BF7: 42217 | BG7: 42248 | BH7: 42278 | BI7: 42309 | BJ7: 42339 | BK7: 42370 | BL7: 42401 | BM7: 42430 | BN7: 42461 | BO7: 42491 | BP7: 42522 | BQ7: 42552 | BR7: 42583 | BS7: 42614 | BT7: 42644 | BU7: 42675 | BV7: 42705 | BW7: 42736 | BX7: 42767 | BY7: 42795 | BZ7: 42826 | CA7: 42856 | CB7: 42887 | CC7: 42917 | CD7: 42948 | CE7: 42979 | CF7: 43009 | CG7: 43040 | CH7: 43070 | CI7: 43101 | CJ7: 43132 | CK7: 43160 | CL7: 43191 | CM7: 43221 | CN7: % Crecimiento | CP7: CONCEPTO | CQ7: CANTIDAD | CR7: % PART.
B8: 40544 | C8: ='Adherencia Mimpara'!D12 -> 5 | D8: ='Adherencia Mimpara'!E12 -> 0 | E8: ='Adherencia Mimpara'!F12 -> 3 | F8: ='Adherencia Mimpara'!G12 -> 1 | G8: ='Adherencia Mimpara'!H12 -> 2 | H8: ='Adherencia Mimpara'!I12 -> 1 | I8: ='Adherencia Mimpara'!J12 -> 2 | J8: ='Adherencia Mimpara'!K12 -> 2 | ... CM8: ='Adherencia Mimpara'!CN12 -> 0 | CN8: =CM8/C8 -> 0 | CP8: PX ADHERENTES | CQ8: =+SUM(CM8:CM95) -> 8 | CR8: =CQ8/$CQ$11 -> 0.0095808383
B9: 40575 | D9: ='Adherencia Mimpara'!E41 -> 26 | E9: ='Adherencia Mimpara'!F41 -> 8 | F9: ='Adherencia Mimpara'!G41 -> 8 | G9: ='Adherencia Mimpara'!H41 -> 5 | H9: ='Adherencia Mimpara'!I41 -> 5 | I9: ='Adherencia Mimpara'!J41 -> 6 | J9: ='Adherencia Mimpara'!K41 -> 2 | K9: ='Adherencia Mimpara'!L41 -> 2 | ... CM9: ='Adherencia Mimpara'!CN41 -> 0 | CN9: =CM9/D9 -> 0 | CP9: PX ABANDONADOS | CQ9: =CQ11-SUM(CQ8,CQ10) -> 815 | CR9: =CQ9/$CQ$11 -> 0.9760479
B10: 40603 | E10: ='Adherencia Mimpara'!F71 -> 27 | F10: ='Adherencia Mimpara'!G71 -> 8 | G10: ='Adherencia Mimpara'!H71 -> 9 | H10: ='Adherencia Mimpara'!I71 -> 7 | I10: ='Adherencia Mimpara'!J71 -> 6 | J10: ='Adherencia Mimpara'!K71 -> 5 | K10: ='Adherencia Mimpara'!L71 -> 5 | L10: ='Adherencia Mimpara'!M71 -> 6 | ... CM10: ='Adherencia Mimpara'!CN71 -> 0 | CN10: =CM10/E10 -> 0 | CP10: PX NVOS MAY 2018 | CQ10: =CM96 -> 12 | CR10: =CQ10/$CQ$11 -> 0.014371257
B11: 40634 | F11: ='Adherencia Mimpara'!G93 -> 19 | G11: ='Adherencia Mimpara'!H93 -> 5 | H11: ='Adherencia Mimpara'!I93 -> 4 | I11: ='Adherencia Mimpara'!J93 -> 1 | J11: ='Adherencia Mimpara'!K93 -> 1 | K11: ='Adherencia Mimpara'!L93 -> 4 | L11: ='Adherencia Mimpara'!M93 -> 0 | M11: ='Adherencia Mimpara'!N93 -> 2 | ... CM11: ='Adherencia Mimpara'!CN93 -> 0 | CN11: =CM11/F11 -> 0 | CP11: PX ACUMULADOS | CQ11: =SUM(C8,D9,E10,F11,G12,I14,H13,J15,K16,L17,M18,N19,O20,P21,Q22,R23,S24,T25,U26,V27,W28,X29,Y30,Z31,AA32,AB33,AC34,AD35,AE36,AF37,AG38,AH39,AI40,AJ41,AK42,AL43,AM44,AN45,AO46,AP47,AQ48,AR49,AS50,AT51,AU52,AV53,AW54,AX55,AY56,AZ57,BA58,BB59,BC60,BD61,BE62,BF63,BG64,BH65,BI66,BJ67,BK68,BL69,BM70,BN71,BO72,BP73,BQ74,BR75,BS76,BT77,BU78,BV79,BW80,BX81,BY82,BZ83,CA84,CB85,CC86,CD87,CE88,CF89,CG90,CH91,CI92,CJ93,CK94,CL95,CM96) -> 835 | CR11: =CQ11/$CQ$11 -> 1
B12: 40664 | G12: ='Adherencia Mimpara'!H116 -> 20 | H12: ='Adherencia Mimpara'!I116 -> 7 | I12: ='Adherencia Mimpara'!J116 -> 8 | J12: ='Adherencia Mimpara'!K116 -> 5 | K12: ='Adherencia Mimpara'!L116 -> 5 | L12: ='Adherencia Mimpara'!M116 -> 2 | M12: ='Adherencia Mimpara'!N116 -> 2 | N12: ='Adherencia Mimpara'!O116 -> 5 | ... CM12: ='Adherencia Mimpara'!CN116 -> 0 | CN12: =CM12/G12 -> 0
B13: 40695 | H13: ='Adherencia Mimpara'!I132 -> 13 | I13: ='Adherencia Mimpara'!J132 -> 4 | J13: ='Adherencia Mimpara'!K132 -> 7 | K13: ='Adherencia Mimpara'!L132 -> 2 | L13: ='Adherencia Mimpara'!M132 -> 2 | M13: ='Adherencia Mimpara'!N132 -> 2 | N13: ='Adherencia Mimpara'!O132 -> 1 | O13: ='Adherencia Mimpara'!P132 -> 1 | ... CM13: ='Adherencia Mimpara'!CN132 -> 0 | CN13: =CM13/H13 -> 0
B14: 40725 | I14: ='Adherencia Mimpara'!J142 -> 7 | J14: ='Adherencia Mimpara'!K142 -> 1 | K14: ='Adherencia Mimpara'!L142 -> 2 | L14: ='Adherencia Mimpara'!M142 -> 2 | M14: ='Adherencia Mimpara'!N142 -> 1 | N14: ='Adherencia Mimpara'!O142 -> 2 | O14: ='Adherencia Mimpara'!P142 -> 2 | P14: ='Adherencia Mimpara'!Q142 -> 2 | ... CM14: ='Adherencia Mimpara'!CN142 -> 0 | CN14: =CM14/I14 -> 0
B15: 40756 | J15: ='Adherencia Mimpara'!K154 -> 9 | K15: ='Adherencia Mimpara'!L154 -> 2 | L15: ='Adherencia Mimpara'!M154 -> 3 | M15: ='Adherencia Mimpara'!N154 -> 2 | N15: ='Adherencia Mimpara'!O154 -> 0 | O15: ='Adherencia Mimpara'!P154 -> 3 | P15: ='Adherencia Mimpara'!Q154 -> 1 | Q15: ='Adherencia Mimpara'!R154 -> 2 | ... CM15: ='Adherencia Mimpara'!CN154 -> 0 | CN15: =CM15/J15 -> 0
B16: 40787 | K16: ='Adherencia Mimpara'!L176 -> 19 | L16: ='Adherencia Mimpara'!M176 -> 9 | M16: ='Adherencia Mimpara'!N176 -> 2 | N16: ='Adherencia Mimpara'!O176 -> 4 | O16: ='Adherencia Mimpara'!P176 -> 1 | P16: ='Adherencia Mimpara'!Q176 -> 2 | Q16: ='Adherencia Mimpara'!R176 -> 1 | R16: ='Adherencia Mimpara'!S176 -> 2 | ... CM16: ='Adherencia Mimpara'!CN176 -> 0 | CN16: =CM16/K16 -> 0
B17: 40817 | L17: ='Adherencia Mimpara'!M206 -> 27 | M17: ='Adherencia Mimpara'!N206 -> 7 | N17: ='Adherencia Mimpara'!O206 -> 2 | O17: ='Adherencia Mimpara'!P206 -> 1 | P17: ='Adherencia Mimpara'!Q206 -> 0 | Q17: ='Adherencia Mimpara'!R206 -> 2 | R17: ='Adherencia Mimpara'!S206 -> 1 | S17: ='Adherencia Mimpara'!T206 -> 2 | ... CM17: ='Adherencia Mimpara'!CN206 -> 0 | CN17: =CM17/L17 -> 0
B18: 40848 | M18: ='Adherencia Mimpara'!N224 -> 15 | N18: ='Adherencia Mimpara'!O224 -> 4 | O18: ='Adherencia Mimpara'!P224 -> 3 | P18: ='Adherencia Mimpara'!Q224 -> 2 | Q18: ='Adherencia Mimpara'!R224 -> 2 | R18: ='Adherencia Mimpara'!S224 -> 2 | S18: ='Adherencia Mimpara'!T224 -> 0 | T18: ='Adherencia Mimpara'!U224 -> 1 | ... CM18: ='Adherencia Mimpara'!CN224 -> 0 | CN18: =CM18/M18 -> 0
B19: 40878 | N19: ='Adherencia Mimpara'!O236 -> 9 | O19: ='Adherencia Mimpara'!P236 -> 1 | P19: ='Adherencia Mimpara'!Q236 -> 1 | Q19: ='Adherencia Mimpara'!R236 -> 0 | R19: ='Adherencia Mimpara'!S236 -> 1 | S19: ='Adherencia Mimpara'!T236 -> 1 | T19: ='Adherencia Mimpara'!U236 -> 0 | U19: ='Adherencia Mimpara'!V236 -> 0 | ... CM19: ='Adherencia Mimpara'!CN236 -> 0 | CN19: =CM19/N19 -> 0
B20: 40909 | O20: ='Adherencia Mimpara'!P247 -> 8 | P20: ='Adherencia Mimpara'!Q247 -> 1 | Q20: ='Adherencia Mimpara'!R247 -> 0 | R20: ='Adherencia Mimpara'!S247 -> 1 | S20: ='Adherencia Mimpara'!T247 -> 0 | T20: ='Adherencia Mimpara'!U247 -> 0 | U20: ='Adherencia Mimpara'!V247 -> 1 | V20: ='Adherencia Mimpara'!W247 -> 0 | ... CM20: ='Adherencia Mimpara'!CN247 -> 0 | CN20: =CM20/O20 -> 0
B21: 40940 | P21: ='Adherencia Mimpara'!Q256 -> 6 | Q21: ='Adherencia Mimpara'!R256 -> 2 | R21: ='Adherencia Mimpara'!S256 -> 3 | S21: ='Adherencia Mimpara'!T256 -> 2 | T21: ='Adherencia Mimpara'!U256 -> 1 | U21: ='Adherencia Mimpara'!V256 -> 1 | V21: ='Adherencia Mimpara'!W256 -> 0 | W21: ='Adherencia Mimpara'!X256 -> 0 | ... CM21: ='Adherencia Mimpara'!CN256 -> 0 | CN21: =CM21/P21 -> 0
B22: 40969 | Q22: ='Adherencia Mimpara'!R275 -> 16 | R22: ='Adherencia Mimpara'!S275 -> 2 | S22: ='Adherencia Mimpara'!T275 -> 4 | T22: ='Adherencia Mimpara'!U275 -> 2 | U22: ='Adherencia Mimpara'!V275 -> 3 | V22: ='Adherencia Mimpara'!W275 -> 2 | W22: ='Adherencia Mimpara'!X275 -> 1 | X22: ='Adherencia Mimpara'!Y275 -> 1 | ... CM22: ='Adherencia Mimpara'!CN275 -> 0 | CN22: =CM22/Q22 -> 0
B23: 41000 | R23: ='Adherencia Mimpara'!S284 -> 6 | S23: ='Adherencia Mimpara'!T284 -> 2 | T23: ='Adherencia Mimpara'!U284 -> 0 | U23: ='Adherencia Mimpara'!V284 -> 0 | V23: ='Adherencia Mimpara'!W284 -> 0 | W23: ='Adherencia Mimpara'!X284 -> 0 | X23: ='Adherencia Mimpara'!Y284 -> 1 | Y23: ='Adherencia Mimpara'!Z284 -> 0 | ... CM23: ='Adherencia Mimpara'!CN284 -> 0 | CN23: =CM23/R23 -> 0
B24: 41030 | S24: ='Adherencia Mimpara'!T298 -> 11 | T24: ='Adherencia Mimpara'!U298 -> 2 | U24: ='Adherencia Mimpara'!V298 -> 3 | V24: ='Adherencia Mimpara'!W298 -> 2 | W24: ='Adherencia Mimpara'!X298 -> 2 | X24: ='Adherencia Mimpara'!Y298 -> 4 | Y24: ='Adherencia Mimpara'!Z298 -> 3 | Z24: ='Adherencia Mimpara'!AA298 -> 2 | ... CM24: ='Adherencia Mimpara'!CN298 -> 0 | CN24: =CM24/S24 -> 0
B25: 41061 | T25: ='Adherencia Mimpara'!U306 -> 5 | U25: ='Adherencia Mimpara'!V306 -> 0 | V25: ='Adherencia Mimpara'!W306 -> 1 | W25: ='Adherencia Mimpara'!X306 -> 0 | X25: ='Adherencia Mimpara'!Y306 -> 0 | Y25: ='Adherencia Mimpara'!Z306 -> 0 | Z25: ='Adherencia Mimpara'!AA306 -> 0 | AA25: ='Adherencia Mimpara'!AB306 -> 0 | ... CM25: ='Adherencia Mimpara'!CN306 -> 0 | CN25: =CM25/T25 -> 0
B26: 41091 | U26: ='Adherencia Mimpara'!V324 -> 15 | V26: ='Adherencia Mimpara'!W324 -> 3 | W26: ='Adherencia Mimpara'!X324 -> 3 | X26: ='Adherencia Mimpara'!Y324 -> 2 | Y26: ='Adherencia Mimpara'!Z324 -> 2 | Z26: ='Adherencia Mimpara'!AA324 -> 2 | AA26: ='Adherencia Mimpara'!AB324 -> 3 | AB26: ='Adherencia Mimpara'!AC324 -> 2 | ... CM26: ='Adherencia Mimpara'!CN324 -> 0 | CN26: =CM26/U26 -> 0
B27: 41122 | V27: ='Adherencia Mimpara'!W337 -> 10 | W27: ='Adherencia Mimpara'!X337 -> 1 | X27: ='Adherencia Mimpara'!Y337 -> 1 | Y27: ='Adherencia Mimpara'!Z337 -> 2 | Z27: ='Adherencia Mimpara'!AA337 -> 2 | AA27: ='Adherencia Mimpara'!AB337 -> 1 | AB27: ='Adherencia Mimpara'!AC337 -> 0 | AC27: ='Adherencia Mimpara'!AD337 -> 0 | ... CM27: ='Adherencia Mimpara'!CN337 -> 0 | CN27: =CM27/V27 -> 0
B28: 41153 | W28: ='Adherencia Mimpara'!X345 -> 5 | X28: ='Adherencia Mimpara'!Y345 -> 0 | Y28: ='Adherencia Mimpara'!Z345 -> 1 | Z28: ='Adherencia Mimpara'!AA345 -> 0 | AA28: ='Adherencia Mimpara'!AB345 -> 1 | AB28: ='Adherencia Mimpara'!AC345 -> 0 | AC28: ='Adherencia Mimpara'!AD345 -> 0 | AD28: ='Adherencia Mimpara'!AE345 -> 1 | ... CM28: ='Adherencia Mimpara'!CN345 -> 0 | CN28: =CM28/W28 -> 0
B29: 41183 | X29: ='Adherencia Mimpara'!Y362 -> 14 | Y29: ='Adherencia Mimpara'!Z362 -> 3 | Z29: ='Adherencia Mimpara'!AA362 -> 0 | AA29: ='Adherencia Mimpara'!AB362 -> 1 | AB29: ='Adherencia Mimpara'!AC362 -> 1 | AC29: ='Adherencia Mimpara'!AD362 -> 0 | AD29: ='Adherencia Mimpara'!AE362 -> 0 | AE29: ='Adherencia Mimpara'!AF362 -> 0 | ... CM29: ='Adherencia Mimpara'!CN362 -> 0 | CN29: =CM29/X29 -> 0
B30: 41214 | Y30: ='Adherencia Mimpara'!Z379 -> 14 | Z30: ='Adherencia Mimpara'!AA379 -> 1 | AA30: ='Adherencia Mimpara'!AB379 -> 2 | AB30: ='Adherencia Mimpara'!AC379 -> 0 | AC30: ='Adherencia Mimpara'!AD379 -> 0 | AD30: ='Adherencia Mimpara'!AE379 -> 1 | AE30: ='Adherencia Mimpara'!AF379 -> 0 | AF30: ='Adherencia Mimpara'!AG379 -> 1 | ... CM30: ='Adherencia Mimpara'!CN379 -> 0 | CN30: =CM30/Y30 -> 0
B31: 41244 | Z31: ='Adherencia Mimpara'!AA393 -> 11 | AA31: ='Adherencia Mimpara'!AB393 -> 3 | AB31: ='Adherencia Mimpara'!AC393 -> 2 | AC31: ='Adherencia Mimpara'!AD393 -> 2 | AD31: ='Adherencia Mimpara'!AE393 -> 2 | AE31: ='Adherencia Mimpara'!AF393 -> 1 | AF31: ='Adherencia Mimpara'!AG393 -> 2 | AG31: ='Adherencia Mimpara'!AH393 -> 2 | ... CM31: ='Adherencia Mimpara'!CN393 -> 0 | CN31: =CM31/Z31 -> 0
B32: 41275 | AA32: ='Adherencia Mimpara'!AB403 -> 7 | AB32: ='Adherencia Mimpara'!AC403 -> 2 | AC32: ='Adherencia Mimpara'!AD403 -> 1 | AD32: ='Adherencia Mimpara'!AE403 -> 1 | AE32: ='Adherencia Mimpara'!AF403 -> 1 | AF32: ='Adherencia Mimpara'!AG403 -> 2 | AG32: ='Adherencia Mimpara'!AH403 -> 2 | AH32: ='Adherencia Mimpara'!AI403 -> 0 | ... CM32: ='Adherencia Mimpara'!CN403 -> 0 | CN32: =CM32/AA32 -> 0
B33: 41306 | AB33: ='Adherencia Mimpara'!AC417 -> 11 | AC33: ='Adherencia Mimpara'!AD417 -> 1 | AD33: ='Adherencia Mimpara'!AE417 -> 2 | AE33: ='Adherencia Mimpara'!AF417 -> 1 | AF33: ='Adherencia Mimpara'!AG417 -> 0 | AG33: ='Adherencia Mimpara'!AH417 -> 0 | AH33: ='Adherencia Mimpara'!AI417 -> 0 | AI33: ='Adherencia Mimpara'!AJ417 -> 0 | ... CM33: ='Adherencia Mimpara'!CN417 -> 0 | CN33: =CM33/AB33 -> 0
B34: 41334 | AC34: ='Adherencia Mimpara'!AD435 -> 15 | AD34: ='Adherencia Mimpara'!AE435 -> 3 | AE34: ='Adherencia Mimpara'!AF435 -> 5 | AF34: ='Adherencia Mimpara'!AG435 -> 4 | AG34: ='Adherencia Mimpara'!AH435 -> 1 | AH34: ='Adherencia Mimpara'!AI435 -> 2 | AI34: ='Adherencia Mimpara'!AJ435 -> 1 | AJ34: ='Adherencia Mimpara'!AK435 -> 2 | ... CM34: ='Adherencia Mimpara'!CN435 -> 0 | CN34: =CM34/AC34 -> 0
B35: 41365 | AD35: ='Adherencia Mimpara'!AE452 -> 14 | AE35: ='Adherencia Mimpara'!AF452 -> 5 | AF35: ='Adherencia Mimpara'!AG452 -> 5 | AG35: ='Adherencia Mimpara'!AH452 -> 1 | AH35: ='Adherencia Mimpara'!AI452 -> 1 | AI35: ='Adherencia Mimpara'!AJ452 -> 1 | AJ35: ='Adherencia Mimpara'!AK452 -> 1 | AK35: ='Adherencia Mimpara'!AL452 -> 1 | ... CM35: ='Adherencia Mimpara'!CN452 -> 0 | CN35: =CM35/AD35 -> 0
B36: 41395 | AE36: ='Adherencia Mimpara'!AF467 -> 12 | AF36: ='Adherencia Mimpara'!AG467 -> 2 | AG36: ='Adherencia Mimpara'!AH467 -> 3 | AH36: ='Adherencia Mimpara'!AI467 -> 4 | AI36: ='Adherencia Mimpara'!AJ467 -> 3 | AJ36: ='Adherencia Mimpara'!AK467 -> 2 | AK36: ='Adherencia Mimpara'!AL467 -> 2 | AL36: ='Adherencia Mimpara'!AM467 -> 2 | ... CM36: ='Adherencia Mimpara'!CN467 -> 0 | CN36: =CM36/AE36 -> 0
B37: 41426 | AF37: ='Adherencia Mimpara'!AG479 -> 9 | AG37: ='Adherencia Mimpara'!AH479 -> 0 | AH37: ='Adherencia Mimpara'!AI479 -> 0 | AI37: ='Adherencia Mimpara'!AJ479 -> 0 | AJ37: ='Adherencia Mimpara'!AK479 -> 0 | AK37: ='Adherencia Mimpara'!AL479 -> 0 | AL37: ='Adherencia Mimpara'!AM479 -> 0 | AM37: ='Adherencia Mimpara'!AN479 -> 0 | ... CM37: ='Adherencia Mimpara'!CN479 -> 0 | CN37: =CM37/AF37 -> 0
B38: 41456 | AG38: ='Adherencia Mimpara'!AH495 -> 13 | AH38: ='Adherencia Mimpara'!AI495 -> 1 | AI38: ='Adherencia Mimpara'!AJ495 -> 1 | AJ38: ='Adherencia Mimpara'!AK495 -> 1 | AK38: ='Adherencia Mimpara'!AL495 -> 1 | AL38: ='Adherencia Mimpara'!AM495 -> 0 | AM38: ='Adherencia Mimpara'!AN495 -> 0 | AN38: ='Adherencia Mimpara'!AO495 -> 0 | ... CM38: ='Adherencia Mimpara'!CN495 -> 0 | CN38: =CM38/AG38 -> 0
B39: 41487 | AH39: ='Adherencia Mimpara'!AI505 -> 7 | AI39: ='Adherencia Mimpara'!AJ505 -> 2 | AJ39: ='Adherencia Mimpara'!AK505 -> 0 | AK39: ='Adherencia Mimpara'!AL505 -> 0 | AL39: ='Adherencia Mimpara'!AM505 -> 1 | AM39: ='Adherencia Mimpara'!AN505 -> 1 | AN39: ='Adherencia Mimpara'!AO505 -> 0 | AO39: ='Adherencia Mimpara'!AP505 -> 0 | ... CM39: ='Adherencia Mimpara'!CN505 -> 0 | CN39: =CM39/AH39 -> 0
B40: 41518 | AI40: ='Adherencia Mimpara'!AJ515 -> 7 | AJ40: ='Adherencia Mimpara'!AK515 -> 4 | AK40: ='Adherencia Mimpara'!AL515 -> 3 | AL40: ='Adherencia Mimpara'!AM515 -> 1 | AM40: ='Adherencia Mimpara'!AN515 -> 1 | AN40: ='Adherencia Mimpara'!AO515 -> 0 | AO40: ='Adherencia Mimpara'!AP515 -> 0 | AP40: ='Adherencia Mimpara'!AQ515 -> 0 | ... CM40: ='Adherencia Mimpara'!CN515 -> 0 | CN40: =CM40/AI40 -> 0
B41: 41548 | AJ41: ='Adherencia Mimpara'!AK524 -> 6 | AK41: ='Adherencia Mimpara'!AL524 -> 0 | AL41: ='Adherencia Mimpara'!AM524 -> 0 | AM41: ='Adherencia Mimpara'!AN524 -> 1 | AN41: ='Adherencia Mimpara'!AO524 -> 0 | AO41: ='Adherencia Mimpara'!AP524 -> 0 | AP41: ='Adherencia Mimpara'!AQ524 -> 0 | AQ41: ='Adherencia Mimpara'!AR524 -> 0 | ... CM41: ='Adherencia Mimpara'!CN524 -> 0 | CN41: =CM41/AJ41 -> 0
B42: 41579 | AK42: ='Adherencia Mimpara'!AL534 -> 7 | AL42: ='Adherencia Mimpara'!AM534 -> 1 | AM42: ='Adherencia Mimpara'!AN534 -> 1 | AN42: ='Adherencia Mimpara'!AO534 -> 2 | AO42: ='Adherencia Mimpara'!AP534 -> 1 | AP42: ='Adherencia Mimpara'!AQ534 -> 0 | AQ42: ='Adherencia Mimpara'!AR534 -> 1 | AR42: ='Adherencia Mimpara'!AS534 -> 1 | ... CM42: ='Adherencia Mimpara'!CN534 -> 0 | CN42: =CM42/AK42 -> 0
B43: 41609 | AL43: ='Adherencia Mimpara'!AM546 -> 9 | AM43: ='Adherencia Mimpara'!AN546 -> 3 | AN43: ='Adherencia Mimpara'!AO546 -> 0 | AO43: ='Adherencia Mimpara'!AP546 -> 0 | AP43: ='Adherencia Mimpara'!AQ546 -> 1 | AQ43: ='Adherencia Mimpara'!AR546 -> 0 | AR43: ='Adherencia Mimpara'!AS546 -> 0 | AS43: ='Adherencia Mimpara'!AT546 -> 0 | ... CM43: ='Adherencia Mimpara'!CN546 -> 0 | CN43: =CM43/AL43 -> 0
B44: 41640 | AM44: ='Adherencia Mimpara'!AN560 -> 11 | AN44: ='Adherencia Mimpara'!AO560 -> 2 | AO44: ='Adherencia Mimpara'!AP560 -> 1 | AP44: ='Adherencia Mimpara'!AQ560 -> 0 | AQ44: ='Adherencia Mimpara'!AR560 -> 0 | AR44: ='Adherencia Mimpara'!AS560 -> 0 | AS44: ='Adherencia Mimpara'!AT560 -> 0 | AT44: ='Adherencia Mimpara'!AU560 -> 0 | ... CM44: ='Adherencia Mimpara'!CN560 -> 0 | CN44: =CM44/AM44 -> 0
B45: 41671 | AN45: ='Adherencia Mimpara'!AO573 -> 10 | AO45: ='Adherencia Mimpara'!AP573 -> 1 | AP45: ='Adherencia Mimpara'!AQ573 -> 2 | AQ45: ='Adherencia Mimpara'!AR573 -> 0 | AR45: ='Adherencia Mimpara'!AS573 -> 0 | AS45: ='Adherencia Mimpara'!AT573 -> 0 | AT45: ='Adherencia Mimpara'!AU573 -> 0 | AU45: ='Adherencia Mimpara'!AV573 -> 0 | ... CM45: ='Adherencia Mimpara'!CN573 -> 0 | CN45: =CM45/AN45 -> 0
B46: 41699 | AO46: ='Adherencia Mimpara'!AP580 -> 4 | AP46: ='Adherencia Mimpara'!AQ580 -> 1 | AQ46: ='Adherencia Mimpara'!AR580 -> 1 | AR46: ='Adherencia Mimpara'!AS580 -> 0 | AS46: ='Adherencia Mimpara'!AT580 -> 0 | AT46: ='Adherencia Mimpara'!AU580 -> 1 | AU46: ='Adherencia Mimpara'!AV580 -> 1 | AV46: ='Adherencia Mimpara'!AW580 -> 0 | ... CM46: ='Adherencia Mimpara'!CN580 -> 0 | CN46: =CM46/AO46 -> 0
B47: 41730 | AP47: ='Adherencia Mimpara'!AQ593 -> 10 | AQ47: ='Adherencia Mimpara'!AR593 -> 2 | AR47: ='Adherencia Mimpara'!AS593 -> 0 | AS47: ='Adherencia Mimpara'!AT593 -> 2 | AT47: ='Adherencia Mimpara'!AU593 -> 1 | AU47: ='Adherencia Mimpara'!AV593 -> 0 | AV47: ='Adherencia Mimpara'!AW593 -> 1 | AW47: ='Adherencia Mimpara'!AX593 -> 0 | ... CM47: ='Adherencia Mimpara'!CN593 -> 0 | CN47: =CM47/AP47 -> 0
B48: 41760 | AQ48: ='Adherencia Mimpara'!AR601 -> 5 | AR48: ='Adherencia Mimpara'!AS601 -> 0 | AS48: ='Adherencia Mimpara'!AT601 -> 0 | AT48: ='Adherencia Mimpara'!AU601 -> 0 | AU48: ='Adherencia Mimpara'!AV601 -> 0 | AV48: ='Adherencia Mimpara'!AW601 -> 0 | AW48: ='Adherencia Mimpara'!AX601 -> 0 | AX48: ='Adherencia Mimpara'!AY601 -> 0 | ... CM48: ='Adherencia Mimpara'!CN601 -> 0 | CN48: =CM48/AQ48 -> 0
B49: 41791 | AR49: ='Adherencia Mimpara'!AS605 -> 1 | AS49: ='Adherencia Mimpara'!AT605 -> 0 | AT49: ='Adherencia Mimpara'!AU605 -> 1 | AU49: ='Adherencia Mimpara'!AV605 -> 0 | AV49: ='Adherencia Mimpara'!AW605 -> 0 | AW49: ='Adherencia Mimpara'!AX605 -> 0 | AX49: ='Adherencia Mimpara'!AY605 -> 1 | AY49: ='Adherencia Mimpara'!AZ605 -> 0 | ... CM49: ='Adherencia Mimpara'!CN605 -> 0 | CN49: =CM49/AR49 -> 0
B50: 41821 | AS50: ='Adherencia Mimpara'!AT613 -> 5 | AT50: ='Adherencia Mimpara'!AU613 -> 1 | AU50: ='Adherencia Mimpara'!AV613 -> 0 | AV50: ='Adherencia Mimpara'!AW613 -> 1 | AW50: ='Adherencia Mimpara'!AX613 -> 0 | AX50: ='Adherencia Mimpara'!AY613 -> 1 | AY50: ='Adherencia Mimpara'!AZ613 -> 0 | AZ50: ='Adherencia Mimpara'!BA613 -> 0 | ... CM50: ='Adherencia Mimpara'!CN613 -> 0 | CN50: =CM50/AS50 -> 0
B51: 41852 | AT51: ='Adherencia Mimpara'!AU620 -> 4 | AU51: ='Adherencia Mimpara'!AV620 -> 1 | AV51: ='Adherencia Mimpara'!AW620 -> 1 | AW51: ='Adherencia Mimpara'!AX620 -> 1 | AX51: ='Adherencia Mimpara'!AY620 -> 1 | AY51: ='Adherencia Mimpara'!AZ620 -> 0 | AZ51: ='Adherencia Mimpara'!BA620 -> 1 | BA51: ='Adherencia Mimpara'!BB620 -> 1 | ... CM51: ='Adherencia Mimpara'!CN620 -> 0 | CN51: =CM51/AT51 -> 0
B52: 41883 | AU52: ='Adherencia Mimpara'!AV627 -> 4 | AV52: ='Adherencia Mimpara'!AW627 -> 0 | AW52: ='Adherencia Mimpara'!AX627 -> 0 | AX52: ='Adherencia Mimpara'!AY627 -> 0 | AY52: ='Adherencia Mimpara'!AZ627 -> 0 | AZ52: ='Adherencia Mimpara'!BA627 -> 0 | BA52: ='Adherencia Mimpara'!BB627 -> 0 | BB52: ='Adherencia Mimpara'!BC627 -> 0 | ... CM52: ='Adherencia Mimpara'!CN627 -> 0 | CN52: =CM52/AU52 -> 0
B53: 41913 | AV53: ='Adherencia Mimpara'!AW636 -> 6 | AW53: ='Adherencia Mimpara'!AX636 -> 0 | AX53: ='Adherencia Mimpara'!AY636 -> 1 | AY53: ='Adherencia Mimpara'!AZ636 -> 0 | AZ53: ='Adherencia Mimpara'!BA636 -> 1 | BA53: ='Adherencia Mimpara'!BB636 -> 1 | BB53: ='Adherencia Mimpara'!BC636 -> 2 | BC53: ='Adherencia Mimpara'!BD636 -> 0 | ... CM53: ='Adherencia Mimpara'!CN636 -> 0 | CN53: =CM53/AV53 -> 0
B54: 41944 | AW54: ='Adherencia Mimpara'!AX643 -> 4 | AX54: ='Adherencia Mimpara'!AY643 -> 1 | AY54: ='Adherencia Mimpara'!AZ643 -> 1 | AZ54: ='Adherencia Mimpara'!BA643 -> 1 | BA54: ='Adherencia Mimpara'!BB643 -> 0 | BB54: ='Adherencia Mimpara'!BC643 -> 0 | BC54: ='Adherencia Mimpara'!BD643 -> 1 | BD54: ='Adherencia Mimpara'!BE643 -> 0 | ... CM54: ='Adherencia Mimpara'!CN643 -> 0 | CN54: =CM54/AW54 -> 0
B55: 41974 | AX55: ='Adherencia Mimpara'!AY655 -> 9 | AY55: ='Adherencia Mimpara'!AZ655 -> 0 | AZ55: ='Adherencia Mimpara'!BA655 -> 3 | BA55: ='Adherencia Mimpara'!BB655 -> 1 | BB55: ='Adherencia Mimpara'!BC655 -> 1 | BC55: ='Adherencia Mimpara'!BD655 -> 1 | BD55: ='Adherencia Mimpara'!BE655 -> 1 | BE55: ='Adherencia Mimpara'!BF655 -> 2 | ... CM55: ='Adherencia Mimpara'!CN655 -> 0 | CN55: =CM55/AX55 -> 0
B56: 42005 | AY56: ='Adherencia Mimpara'!AZ660 -> 2 | AZ56: ='Adherencia Mimpara'!BA660 -> 0 | BA56: ='Adherencia Mimpara'!BB660 -> 1 | BB56: ='Adherencia Mimpara'!BC660 -> 0 | BC56: ='Adherencia Mimpara'!BD660 -> 0 | BD56: ='Adherencia Mimpara'!BE660 -> 0 | BE56: ='Adherencia Mimpara'!BF660 -> 0 | BF56: ='Adherencia Mimpara'!BG660 -> 0 | ... CM56: ='Adherencia Mimpara'!CN660 -> 0 | CN56: =CM56/AY56 -> 0
B57: 42036 | AZ57: ='Adherencia Mimpara'!BA666 -> 3 | BA57: ='Adherencia Mimpara'!BB666 -> 0 | BB57: ='Adherencia Mimpara'!BC666 -> 1 | BC57: ='Adherencia Mimpara'!BD666 -> 1 | BD57: ='Adherencia Mimpara'!BE666 -> 0 | BE57: ='Adherencia Mimpara'!BF666 -> 0 | BF57: ='Adherencia Mimpara'!BG666 -> 1 | BG57: ='Adherencia Mimpara'!BH666 -> 1 | ... CM57: ='Adherencia Mimpara'!CN666 -> 0 | CN57: =CM57/AZ57 -> 0
B58: 42064 | BA58: ='Adherencia Mimpara'!BB674 -> 4 | BB58: ='Adherencia Mimpara'!BC674 -> 0 | BC58: ='Adherencia Mimpara'!BD674 -> 0 | BD58: ='Adherencia Mimpara'!BE674 -> 0 | BE58: ='Adherencia Mimpara'!BF674 -> 0 | BF58: ='Adherencia Mimpara'!BG674 -> 0 | BG58: ='Adherencia Mimpara'!BH674 -> 0 | BH58: ='Adherencia Mimpara'!BI674 -> 1 | ... CM58: ='Adherencia Mimpara'!CN674 -> 0 | CN58: =CM58/BA58 -> 0
B59: 42095 | BB59: ='Adherencia Mimpara'!BC682 -> 5 | BC59: ='Adherencia Mimpara'!BD682 -> 3 | BD59: ='Adherencia Mimpara'!BE682 -> 0 | BE59: ='Adherencia Mimpara'!BF682 -> 2 | BF59: ='Adherencia Mimpara'!BG682 -> 0 | BG59: ='Adherencia Mimpara'!BH682 -> 0 | BH59: ='Adherencia Mimpara'!BI682 -> 1 | BI59: ='Adherencia Mimpara'!BJ682 -> 0 | ... CM59: ='Adherencia Mimpara'!CN682 -> 0 | CN59: =CM59/BB59 -> 0
B60: 42125 | BC60: ='Adherencia Mimpara'!BD692 -> 7 | BD60: ='Adherencia Mimpara'!BE692 -> 0 | BE60: ='Adherencia Mimpara'!BF692 -> 3 | BF60: ='Adherencia Mimpara'!BG692 -> 1 | BG60: ='Adherencia Mimpara'!BH692 -> 1 | BH60: ='Adherencia Mimpara'!BI692 -> 0 | BI60: ='Adherencia Mimpara'!BJ692 -> 0 | BJ60: ='Adherencia Mimpara'!BK692 -> 0 | ... CM60: ='Adherencia Mimpara'!CN692 -> 0 | CN60: =CM60/BC60 -> 0
B61: 42156 | BD61: ='Adherencia Mimpara'!BE709 -> 13 | BE61: ='Adherencia Mimpara'!BF709 -> 1 | BF61: ='Adherencia Mimpara'!BG709 -> 1 | BG61: ='Adherencia Mimpara'!BH709 -> 3 | BH61: ='Adherencia Mimpara'!BI709 -> 1 | BI61: ='Adherencia Mimpara'!BJ709 -> 2 | BJ61: ='Adherencia Mimpara'!BK709 -> 2 | BK61: ='Adherencia Mimpara'!BL709 -> 2 | ... CM61: ='Adherencia Mimpara'!CN709 -> 1 | CN61: =CM61/BD61 -> 0.076923077
B62: 42186 | BE62: ='Adherencia Mimpara'!BF724 -> 11 | BF62: ='Adherencia Mimpara'!BG724 -> 4 | BG62: ='Adherencia Mimpara'!BH724 -> 2 | BH62: ='Adherencia Mimpara'!BI724 -> 4 | BI62: ='Adherencia Mimpara'!BJ724 -> 2 | BJ62: ='Adherencia Mimpara'!BK724 -> 0 | BK62: ='Adherencia Mimpara'!BL724 -> 1 | BL62: ='Adherencia Mimpara'!BM724 -> 0 | ... CM62: ='Adherencia Mimpara'!CN724 -> 0 | CN62: =CM62/BE62 -> 0
B63: 42217 | BF63: ='Adherencia Mimpara'!BG731 -> 4 | BG63: ='Adherencia Mimpara'!BH731 -> 0 | BH63: ='Adherencia Mimpara'!BI731 -> 1 | BI63: ='Adherencia Mimpara'!BJ731 -> 0 | BJ63: ='Adherencia Mimpara'!BK731 -> 0 | BK63: ='Adherencia Mimpara'!BL731 -> 1 | BL63: ='Adherencia Mimpara'!BM731 -> 1 | BM63: ='Adherencia Mimpara'!BN731 -> 0 | ... CM63: ='Adherencia Mimpara'!CN731 -> 0 | CN63: =CM63/BF63 -> 0
B64: 42248 | BG64: ='Adherencia Mimpara'!BH746 -> 12 | BH64: ='Adherencia Mimpara'!BI746 -> 4 | BI64: ='Adherencia Mimpara'!BJ746 -> 3 | BJ64: ='Adherencia Mimpara'!BK746 -> 1 | BK64: ='Adherencia Mimpara'!BL746 -> 3 | BL64: ='Adherencia Mimpara'!BM746 -> 2 | BM64: ='Adherencia Mimpara'!BN746 -> 1 | BN64: ='Adherencia Mimpara'!BO746 -> 0 | ... CM64: ='Adherencia Mimpara'!CN746 -> 0 | CN64: =CM64/BG64 -> 0
B65: 42278 | BH65: ='Adherencia Mimpara'!BI762 -> 13 | BI65: ='Adherencia Mimpara'!BJ762 -> 0 | BJ65: ='Adherencia Mimpara'!BK762 -> 1 | BK65: ='Adherencia Mimpara'!BL762 -> 0 | BL65: ='Adherencia Mimpara'!BM762 -> 0 | BM65: ='Adherencia Mimpara'!BN762 -> 1 | BN65: ='Adherencia Mimpara'!BO762 -> 0 | BO65: ='Adherencia Mimpara'!BP762 -> 0 | ... CM65: ='Adherencia Mimpara'!CN762 -> 0 | CN65: =CM65/BH65 -> 0
B66: 42309 | BI66: ='Adherencia Mimpara'!BJ772 -> 7 | BJ66: ='Adherencia Mimpara'!BK772 -> 2 | BK66: ='Adherencia Mimpara'!BL772 -> 3 | BL66: ='Adherencia Mimpara'!BM772 -> 0 | BM66: ='Adherencia Mimpara'!BN772 -> 0 | BN66: ='Adherencia Mimpara'!BO772 -> 1 | BO66: ='Adherencia Mimpara'!BP772 -> 1 | BP66: ='Adherencia Mimpara'!BQ772 -> 0 | ... CM66: ='Adherencia Mimpara'!CN772 -> 0 | CN66: =CM66/BI66 -> 0
B67: 42339 | BJ67: ='Adherencia Mimpara'!BK783 -> 8 | BK67: ='Adherencia Mimpara'!BL783 -> 0 | BL67: ='Adherencia Mimpara'!BM783 -> 1 | BM67: ='Adherencia Mimpara'!BN783 -> 2 | BN67: ='Adherencia Mimpara'!BO783 -> 0 | BO67: ='Adherencia Mimpara'!BP783 -> 1 | BP67: ='Adherencia Mimpara'!BQ783 -> 0 | BQ67: ='Adherencia Mimpara'!BR783 -> 1 | ... CM67: ='Adherencia Mimpara'!CN783 -> 0 | CN67: =CM67/BJ67 -> 0
B68: 42370 | BK68: ='Adherencia Mimpara'!BL795 -> 9 | BL68: ='Adherencia Mimpara'!BM795 -> 0 | BM68: ='Adherencia Mimpara'!BN795 -> 0 | BN68: ='Adherencia Mimpara'!BO795 -> 1 | BO68: ='Adherencia Mimpara'!BP795 -> 0 | BP68: ='Adherencia Mimpara'!BQ795 -> 0 | BQ68: ='Adherencia Mimpara'!BR795 -> 0 | BR68: ='Adherencia Mimpara'!BS795 -> 0 | ... CM68: ='Adherencia Mimpara'!CN795 -> 0 | CN68: =CM68/BK68 -> 0
B69: 42401 | BL69: ='Adherencia Mimpara'!BM802 -> 1 | BM69: ='Adherencia Mimpara'!BN803 -> 1 | BN69: ='Adherencia Mimpara'!BO803 -> 1 | BO69: ='Adherencia Mimpara'!BP803 -> 1 | BP69: ='Adherencia Mimpara'!BQ803 -> 3 | BQ69: ='Adherencia Mimpara'!BR803 -> 1 | BR69: ='Adherencia Mimpara'!BS803 -> 1 | BS69: ='Adherencia Mimpara'!BT803 -> 1 | BT69: ='Adherencia Mimpara'!BU803 -> 0 | ... CM69: ='Adherencia Mimpara'!CN803 -> 0 | CN69: =CM69/BL69 -> 0
B70: 42430 | BM70: ='Adherencia Mimpara'!BN821 -> 15 | BN70: ='Adherencia Mimpara'!BO821 -> 1 | BO70: ='Adherencia Mimpara'!BP821 -> 0 | BP70: ='Adherencia Mimpara'!BQ821 -> 2 | BQ70: ='Adherencia Mimpara'!BR821 -> 0 | BR70: ='Adherencia Mimpara'!BS821 -> 1 | BS70: ='Adherencia Mimpara'!BT821 -> 0 | BT70: ='Adherencia Mimpara'!BU821 -> 0 | ... CM70: ='Adherencia Mimpara'!CN821 -> 0 | CN70: =CM70/BM70 -> 0
B71: 42461 | BN71: ='Adherencia Mimpara'!BO830 -> 6 | BO71: ='Adherencia Mimpara'!BP830 -> 2 | BP71: ='Adherencia Mimpara'!BQ830 -> 0 | BQ71: ='Adherencia Mimpara'!BR830 -> 1 | BR71: ='Adherencia Mimpara'!BS830 -> 1 | BS71: ='Adherencia Mimpara'!BT830 -> 0 | BT71: ='Adherencia Mimpara'!BU830 -> 0 | BU71: ='Adherencia Mimpara'!BV830 -> 1 | ... CM71: ='Adherencia Mimpara'!CN830 -> 0 | CN71: =CM71/BN71 -> 0
B72: 42491 | BO72: ='Adherencia Mimpara'!BP842 -> 9 | BP72: ='Adherencia Mimpara'!BQ842 -> 1 | BQ72: ='Adherencia Mimpara'!BR842 -> 4 | BR72: ='Adherencia Mimpara'!BS842 -> 0 | BS72: ='Adherencia Mimpara'!BT842 -> 2 | BT72: ='Adherencia Mimpara'!BU842 -> 3 | BU72: ='Adherencia Mimpara'!BV842 -> 1 | BV72: ='Adherencia Mimpara'!BW842 -> 1 | ... CM72: ='Adherencia Mimpara'!CN842 -> 0 | CN72: =CM72/BO72 -> 0
B73: 42522 | BP73: ='Adherencia Mimpara'!BQ851 -> 6 | BQ73: ='Adherencia Mimpara'!BR851 -> 1 | BR73: ='Adherencia Mimpara'!BS851 -> 0 | BS73: ='Adherencia Mimpara'!BT851 -> 1 | BT73: ='Adherencia Mimpara'!BU851 -> 1 | BU73: ='Adherencia Mimpara'!BV851 -> 0 | BV73: ='Adherencia Mimpara'!BW851 -> 0 | BW73: ='Adherencia Mimpara'!BX851 -> 0 | ... CM73: ='Adherencia Mimpara'!CN851 -> 0 | CN73: =CM73/BP73 -> 0
B74: 42552 | BQ74: ='Adherencia Mimpara'!BR858 -> 4 | BR74: ='Adherencia Mimpara'!BS858 -> 2 | BS74: ='Adherencia Mimpara'!BT858 -> 1 | BT74: ='Adherencia Mimpara'!BU858 -> 1 | BU74: ='Adherencia Mimpara'!BV858 -> 0 | BV74: ='Adherencia Mimpara'!BW858 -> 0 | BW74: ='Adherencia Mimpara'!BX858 -> 1 | BX74: ='Adherencia Mimpara'!BY858 -> 0 | ... CM74: ='Adherencia Mimpara'!CN858 -> 0 | CN74: =CM74/BQ74 -> 0
B75: 42583 | BR75: ='Adherencia Mimpara'!BS868 -> 7 | BS75: ='Adherencia Mimpara'!BT868 -> 2 | BT75: ='Adherencia Mimpara'!BU868 -> 3 | BU75: ='Adherencia Mimpara'!BV868 -> 2 | BV75: ='Adherencia Mimpara'!BW868 -> 3 | BW75: ='Adherencia Mimpara'!BX868 -> 2 | BX75: ='Adherencia Mimpara'!BY868 -> 2 | BY75: ='Adherencia Mimpara'!BZ868 -> 1 | ... CM75: ='Adherencia Mimpara'!CN868 -> 1 | CN75: =CM75/BR75 -> 0.14285714
B76: 42614 | BS76: ='Adherencia Mimpara'!BT880 -> 9 | BT76: ='Adherencia Mimpara'!BU880 -> 2 | BU76: ='Adherencia Mimpara'!BV880 -> 1 | BV76: ='Adherencia Mimpara'!BW880 -> 4 | BW76: ='Adherencia Mimpara'!BX880 -> 1 | BX76: ='Adherencia Mimpara'!BY880 -> 3 | BY76: ='Adherencia Mimpara'!BZ880 -> 2 | BZ76: ='Adherencia Mimpara'!CA880 -> 2 | ... CM76: ='Adherencia Mimpara'!CN880 -> 1 | CN76: =CM76/BS76 -> 0.11111111
B77: 42644 | BT77: ='Adherencia Mimpara'!BU893 -> 10 | BU77: ='Adherencia Mimpara'!BV893 -> 1 | BV77: ='Adherencia Mimpara'!BW893 -> 2 | BW77: ='Adherencia Mimpara'!BX893 -> 2 | BX77: ='Adherencia Mimpara'!BY893 -> 1 | BY77: ='Adherencia Mimpara'!BZ893 -> 0 | BZ77: ='Adherencia Mimpara'!CA893 -> 1 | CA77: ='Adherencia Mimpara'!CB893 -> 2 | ... CM77: ='Adherencia Mimpara'!CN893 -> 0 | CN77: =CM77/BT77 -> 0
B78: 42675 | BU78: ='Adherencia Mimpara'!BV906 -> 10 | BV78: ='Adherencia Mimpara'!BW906 -> 0 | BW78: ='Adherencia Mimpara'!BX906 -> 0 | BX78: ='Adherencia Mimpara'!BY906 -> 0 | BY78: ='Adherencia Mimpara'!BZ906 -> 1 | BZ78: ='Adherencia Mimpara'!CA906 -> 0 | CA78: ='Adherencia Mimpara'!CB906 -> 1 | CB78: ='Adherencia Mimpara'!CC906 -> 0 | ... CM78: ='Adherencia Mimpara'!CN906 -> 0 | CN78: =CM78/BU78 -> 0
B79: 42705 | BV79: ='Adherencia Mimpara'!BW917 -> 8 | BW79: ='Adherencia Mimpara'!BX917 -> 0 | BX79: ='Adherencia Mimpara'!BY917 -> 0 | BY79: ='Adherencia Mimpara'!BZ917 -> 0 | BZ79: ='Adherencia Mimpara'!CA917 -> 0 | CA79: ='Adherencia Mimpara'!CB917 -> 1 | CB79: ='Adherencia Mimpara'!CC917 -> 2 | CC79: ='Adherencia Mimpara'!CD917 -> 2 | ... CM79: ='Adherencia Mimpara'!CN917 -> 0 | CN79: =CM79/BV79 -> 0
B80: 42736 | BW80: ='Adherencia Mimpara'!BX924 -> 4 | BX80: ='Adherencia Mimpara'!BY924 -> 1 | BY80: ='Adherencia Mimpara'!BZ924 -> 1 | BZ80: ='Adherencia Mimpara'!CA924 -> 1 | CA80: ='Adherencia Mimpara'!CB924 -> 1 | CB80: ='Adherencia Mimpara'!CC924 -> 1 | CC80: ='Adherencia Mimpara'!CD924 -> 1 | CD80: ='Adherencia Mimpara'!CE924 -> 1 | ... CM80: ='Adherencia Mimpara'!CN924 -> 0 | CN80: =CM80/BW80 -> 0
B81: 42767 | BX81: ='Adherencia Mimpara'!BY935 -> 8 | BY81: ='Adherencia Mimpara'!BZ935 -> 1 | BZ81: ='Adherencia Mimpara'!CA935 -> 2 | CA81: ='Adherencia Mimpara'!CB935 -> 0 | CB81: ='Adherencia Mimpara'!CC935 -> 1 | CC81: ='Adherencia Mimpara'!CD935 -> 1 | CD81: ='Adherencia Mimpara'!CE935 -> 0 | CE81: ='Adherencia Mimpara'!CF935 -> 1 | ... CM81: ='Adherencia Mimpara'!CN935 -> 0 | CN81: =CM81/BX81 -> 0
B82: 42795 | BY82: ='Adherencia Mimpara'!BZ954 -> 16 | BZ82: ='Adherencia Mimpara'!CA954 -> 4 | CA82: ='Adherencia Mimpara'!CB954 -> 4 | CB82: ='Adherencia Mimpara'!CC954 -> 3 | CC82: ='Adherencia Mimpara'!CD954 -> 5 | CD82: ='Adherencia Mimpara'!CE954 -> 2 | CE82: ='Adherencia Mimpara'!CF954 -> 1 | CF82: ='Adherencia Mimpara'!CG954 -> 3 | ... CM82: ='Adherencia Mimpara'!CN954 -> 1 | CN82: =CM82/BY82 -> 0.0625
B83: 42826 | BZ83: ='Adherencia Mimpara'!CA970 -> 12 | CA83: ='Adherencia Mimpara'!CB970 -> 2 | CB83: ='Adherencia Mimpara'!CC970 -> 1 | CC83: ='Adherencia Mimpara'!CD970 -> 2 | CD83: ='Adherencia Mimpara'!CE970 -> 1 | CE83: ='Adherencia Mimpara'!CF970 -> 2 | CF83: ='Adherencia Mimpara'!CG970 -> 1 | CG83: ='Adherencia Mimpara'!CH970 -> 1 | ... CM83: ='Adherencia Mimpara'!CN970 -> 1 | CN83: =CM83/BZ83 -> 0.083333333
B84: 42856 | CA84: ='Adherencia Mimpara'!CB983 -> 9 | CB84: ='Adherencia Mimpara'!CC983 -> 0 | CC84: ='Adherencia Mimpara'!CD983 -> 0 | CD84: ='Adherencia Mimpara'!CE983 -> 0 | CE84: ='Adherencia Mimpara'!CF983 -> 2 | CF84: ='Adherencia Mimpara'!CG983 -> 0 | CG84: ='Adherencia Mimpara'!CH983 -> 0 | CH84: ='Adherencia Mimpara'!CI983 -> 1 | ... CM84: ='Adherencia Mimpara'!CN983 -> 0 | CN84: =CM84/CA84 -> 0
B85: 42887 | CB85: ='Adherencia Mimpara'!CC995 -> 8 | CC85: ='Adherencia Mimpara'!CD995 -> 1 | CD85: ='Adherencia Mimpara'!CE995 -> 1 | CE85: ='Adherencia Mimpara'!CF995 -> 2 | CF85: ='Adherencia Mimpara'!CG995 -> 0 | CG85: ='Adherencia Mimpara'!CH995 -> 1 | CH85: ='Adherencia Mimpara'!CI995 -> 2 | CI85: ='Adherencia Mimpara'!CJ995 -> 0 | ... CM85: ='Adherencia Mimpara'!CN995 -> 0 | CN85: =CM85/CB85 -> 0
B86: 42917 | CC86: ='Adherencia Mimpara'!CD1008 -> 9 | CD86: ='Adherencia Mimpara'!CE1008 -> 3 | CE86: ='Adherencia Mimpara'!CF1008 -> 2 | CF86: ='Adherencia Mimpara'!CG1008 -> 2 | CG86: ='Adherencia Mimpara'!CH1008 -> 2 | CH86: ='Adherencia Mimpara'!CI1008 -> 1 | CI86: ='Adherencia Mimpara'!CJ1008 -> 1 | CJ86: ='Adherencia Mimpara'!CK1008 -> 3 | ... CM86: ='Adherencia Mimpara'!CN1008 -> 1 | CN86: =CM86/CC86 -> 0.11111111
B87: 42948 | CD87: ='Adherencia Mimpara'!CE1017 -> 5 | CE87: ='Adherencia Mimpara'!CF1017 -> 2 | CF87: ='Adherencia Mimpara'!CG1017 -> 1 | CG87: ='Adherencia Mimpara'!CH1017 -> 1 | CH87: ='Adherencia Mimpara'!CI1017 -> 0 | CI87: ='Adherencia Mimpara'!CJ1017 -> 0 | CJ87: ='Adherencia Mimpara'!CK1017 -> 0 | CK87: ='Adherencia Mimpara'!CL1017 -> 0 | ... CM87: ='Adherencia Mimpara'!CN1017 -> 0 | CN87: =CM87/CD87 -> 0
B88: 42979 | CE88: ='Adherencia Mimpara'!CF1033 -> 12 | CF88: ='Adherencia Mimpara'!CG1033 -> 3 | CG88: ='Adherencia Mimpara'!CH1033 -> 2 | CH88: ='Adherencia Mimpara'!CI1033 -> 0 | CI88: ='Adherencia Mimpara'!CJ1033 -> 1 | CJ88: ='Adherencia Mimpara'!CK1033 -> 0 | CK88: ='Adherencia Mimpara'!CL1033 -> 0 | CL88: ='Adherencia Mimpara'!CM1033 -> 0 | CM88: ='Adherencia Mimpara'!CN1033 -> 0 | CN88: =CM88/CE88 -> 0
B89: 43009 | CF89: ='Adherencia Mimpara'!CG1043 -> 7 | CG89: ='Adherencia Mimpara'!CH1043 -> 1 | CH89: ='Adherencia Mimpara'!CI1043 -> 1 | CI89: ='Adherencia Mimpara'!CJ1043 -> 0 | CJ89: ='Adherencia Mimpara'!CK1043 -> 1 | CK89: ='Adherencia Mimpara'!CL1043 -> 0 | CL89: ='Adherencia Mimpara'!CM1043 -> 0 | CM89: ='Adherencia Mimpara'!CN1043 -> 0 | CN89: =CM89/CF89 -> 0
B90: 43040 | CG90: ='Adherencia Mimpara'!CH1051 -> 5 | CH90: ='Adherencia Mimpara'!CI1051 -> 1 | CI90: ='Adherencia Mimpara'!CJ1051 -> 0 | CJ90: ='Adherencia Mimpara'!CK1051 -> 1 | CK90: ='Adherencia Mimpara'!CL1051 -> 2 | CL90: ='Adherencia Mimpara'!CM1051 -> 0 | CM90: ='Adherencia Mimpara'!CN1051 -> 0 | CN90: =CM90/CG90 -> 0
B91: 43070 | CH91: ='Adherencia Mimpara'!CI1060 -> 6 | CI91: ='Adherencia Mimpara'!CJ1060 -> 1 | CJ91: ='Adherencia Mimpara'!CK1060 -> 1 | CK91: ='Adherencia Mimpara'!CL1060 -> 1 | CL91: ='Adherencia Mimpara'!CM1060 -> 0 | CM91: ='Adherencia Mimpara'!CN1060 -> 0 | CN91: =CM91/CH91 -> 0
B92: 43101 | CI92: ='Adherencia Mimpara'!CJ1075 -> 12 | CJ92: ='Adherencia Mimpara'!CK1075 -> 1 | CK92: ='Adherencia Mimpara'!CL1075 -> 1 | CL92: ='Adherencia Mimpara'!CM1075 -> 0 | CM92: ='Adherencia Mimpara'!CN1075 -> 1 | CN92: =CM92/CI92 -> 0.083333333
B93: 43132 | CJ93: ='Adherencia Mimpara'!CK1084 -> 6 | CK93: ='Adherencia Mimpara'!CL1084 -> 1 | CL93: ='Adherencia Mimpara'!CM1084 -> 0 | CM93: ='Adherencia Mimpara'!CN1084 -> 1 | CN93: =CM93/CJ93 -> 0.16666667
B94: 43160 | CK94: ='Adherencia Mimpara'!CL1096 -> 9 | CL94: ='Adherencia Mimpara'!CM1096 -> 0 | CM94: ='Adherencia Mimpara'!CN1096 -> 0 | CN94: =CM94/CK94 -> 0
B95: 43191 | CL95: ='Adherencia Mimpara'!CM1104 -> 5 | CM95: ='Adherencia Mimpara'!CN1104 -> 0 | CN95: =IFERROR(CM95/CL95,0) -> 0
B96: 43221 | CM96: ='Adherencia Mimpara'!CN1119 -> 12 | CN96: =IFERROR(CM96/CM96,0) -> 1
B97: Total general | C97: =SUM(C8:C96) -> 5 | D97: =SUM(D8:D96) -> 26 | E97: =SUM(E8:E96) -> 38 | F97: =SUM(F8:F96) -> 36 | G97: =SUM(G8:G96) -> 41 | H97: =SUM(H8:H96) -> 37 | I97: =SUM(I8:I96) -> 34 | J97: =SUM(J8:J96) -> 32 | ... CM97: =SUM(CM8:CM96) -> 20
B100: PACIENTES NUEVOS Y ADHERENTES POR PERIODO | CP100: ADHERENCIA EN PORCENTAJES | GD100: ABANDONO
C101: MES 1 | D101: MES 2 | E101: MES 3 | F101: MES 4 | G101: MES 5 | H101: MES 6 | I101: MES 7 | J101: MES 8 | K101: MES 9 | L101: MES 10 | M101: MES 11 | N101: MES 12 | O101: MES 13 | P101: MES 14 | Q101: MES 15 | R101: MES 16 | S101: MES 17 | T101: MES 18 | U101: MES 19 | V101: MES 20 | W101: MES 21 | X101: MES 22 | Y101: MES 23 | Z101: MES 24 | AA101: MES 25 | AB101: MES 26 | AC101: MES 27 | AD101: MES 28 | AE101: MES 29 | AF101: MES 30 | AG101: MES 31 | AH101: MES 32 | AI101: MES 33 | AJ101: MES 34 | AK101: MES 35 | AL101: MES 36 | AM101: MES 37 | AN101: MES 38 | AO101: MES 39 | AP101: MES 40 | AQ101: MES 41 | AR101: MES 42 | AS101: MES 43 | AT101: MES 44 | AU101: MES 45 | AV101: MES 46 | AW101: MES 47 | AX101: MES 48 | AY101: MES 49 | AZ101: MES 50 | BA101: MES 51 | BB101: MES 52 | BC101: MES 53 | BD101: MES 54 | BE101: MES 55 | BF101: MES 56 | BG101: MES 57 | BH101: MES 58 | BI101: MES 59 | BJ101: MES 60 | BK101: MES 61 | BL101: MES 62 | BM101: MES 63 | BN101: MES 64 | BO101: MES 65 | BP101: MES 66 | BQ101: MES 67 | BR101: MES 68 | BS101: MES 69 | BT101: MES 70 | BU101: MES 71 | BV101: MES 72 | BW101: MES 73 | BX101: MES 74 | BY101: MES 75 | BZ101: MES 76 | CA101: MES 77 | CB101: MES 78 | CC101: MES 79 | CD101: MES 80 | CE101: MES 81 | CF101: MES 82 | CG101: MES 83 | CH101: MES 84 | CI101: MES 85 | CJ101: MES 86 | CK101: MES 87 | CL101: MES 88 | CM101: MES 89 | CQ101: MES 1 | CR101: MES 2 | CS101: MES 3 | CT101: MES 4 | CU101: MES 5 | CV101: MES 6 | CW101: MES 7 | CX101: MES 8 | CY101: MES 9 | CZ101: MES 10 | DA101: MES 11 | DB101: MES 12 | DC101: MES 13 | DD101: MES 14 | DE101: MES 15 | DF101: MES 16 | DG101: MES 17 | DH101: MES 18 | DI101: MES 19 | DJ101: MES 20 | DK101: MES 21 | DL101: MES 22 | DM101: MES 23 | DN101: MES 24 | DO101: MES 25 | DP101: MES 26 | DQ101: MES 27 | DR101: MES 28 | DS101: MES 29 | DT101: MES 30 | DU101: MES 31 | DV101: MES 32 | DW101: MES 33 | DX101: MES 34 | DY101: MES 35 | DZ101: MES 36 | EA101: MES 37 | EB101: MES 38 | EC101: MES 39 | ED101: MES 40 | EE101: MES 41 | EF101: MES 42 | EG101: MES 43 | EH101: MES 44 | EI101: MES 45 | EJ101: MES 46 | EK101: MES 47 | EL101: MES 48 | EM101: MES 49 | EN101: MES 50 | EO101: MES 51 | EP101: MES 52 | EQ101: MES 53 | ER101: MES 54 | ES101: MES 55 | ET101: MES 56 | EU101: MES 57 | EV101: MES 58 | EW101: MES 59 | EX101: MES 60 | EY101: MES 61 | EZ101: MES 62 | FA101: MES 63 | FB101: MES 64 | FC101: MES 65 | FD101: MES 66 | FE101: MES 67 | FF101: MES 68 | FG101: MES 69 | FH101: MES 70 | FI101: MES 71 | FJ101: MES 72 | FK101: MES 73 | FL101: MES 74 | FM101: MES 75 | FN101: MES 76 | FO101: MES 77 | FP101: MES 78 | FQ101: MES 79 | FR101: MES 80 | FS101: MES 81 | FT101: MES 82 | FU101: MES 83 | FV101: MES 84 | FW101: MES 85 | FX101: MES 86 | FY101: MES 87 | FZ101: MES 88 | GA101: MES 89 | GE101: MES 1 | GF101: MES 2 | GG101: MES 3 | GH101: MES 4 | GI101: MES 5 | GJ101: MES 6 | GK101: MES 7 | GL101: MES 8 | GM101: MES 9 | GN101: MES 10 | GO101: MES 11 | GP101: MES 12 | GQ101: MES 13 | GR101: MES 14 | GS101: MES 15 | GT101: MES 16 | GU101: MES 17 | GV101: MES 18 | GW101: MES 19 | GX101: MES 20 | GY101: MES 21 | GZ101: MES 22 | HA101: MES 23 | HB101: MES 24 | HC101: MES 25 | HD101: MES 26 | HE101: MES 27 | HF101: MES 28 | HG101: MES 29 | HH101: MES 30 | HI101: MES 31 | HJ101: MES 32 | HK101: MES 33 | HL101: MES 34 | HM101: MES 35 | HN101: MES 36 | HO101: MES 37 | HP101: MES 38 | HQ101: MES 39 | HR101: MES 40 | HS101: MES 41 | HT101: MES 42 | HU101: MES 43 | HV101: MES 44 | HW101: MES 45 | HX101: MES 46 | HY101: MES 47 | HZ101: MES 48 | IA101: MES 49 | IB101: MES 50 | IC101: MES 51 | ID101: MES 52 | IE101: MES 53 | IF101: MES 54 | IG101: MES 55 | IH101: MES 56 | II101: MES 57 | IJ101: MES 58 | IK101: MES 59 | IL101: MES 60 | IM101: MES 61 | IN101: MES 62 | IO101: MES 63 | IP101: MES 64 | IQ101: MES 65 | IR101: MES 66 | IS101: MES 67 | IT101: MES 68 | IU101: MES 69 | IV101: MES 70 | IW101: MES 71 | IX101: MES 72 | IY101: MES 73 | IZ101: MES 74 | JA101: MES 75 | JB101: MES 76 | JC101: MES 77 | JD101: MES 78 | JE101: MES 79 | JF101: MES 80 | JG101: MES 81 | JH101: MES 82 | JI101: MES 83 | JJ101: MES 84 | JK101: MES 85 | JL101: MES 86 | JM101: MES 87 | JN101: MES 88 | JO101: MES 89
B102: 40544 | C102: =C8 -> 5 | D102: =D8 -> 0 | E102: =E8 -> 3 | F102: =F8 -> 1 | G102: =G8 -> 2 | H102: =H8 -> 1 | I102: =I8 -> 2 | J102: =J8 -> 2 | ... CM102: =CM8 -> 0 | CP102: 40544 | CQ102: =C102/$C102 -> 1 | CR102: =D102/$C102 -> 0 | CS102: =E102/$C102 -> 0.6 | CT102: =F102/$C102 -> 0.2 | CU102: =G102/$C102 -> 0.4 | CV102: =H102/$C102 -> 0.2 | CW102: =I102/$C102 -> 0.4 | CX102: =J102/$C102 -> 0.4 | ... GA102: =CM102/$C102 -> 0 | GD102: 40544 | GE102: =1-CQ102 -> 0 | GF102: =1-CR102 -> 1 | GG102: =1-CS102 -> 0.4 | GH102: =1-CT102 -> 0.8 | GI102: =1-CU102 -> 0.6 | GJ102: =1-CV102 -> 0.8 | GK102: =1-CW102 -> 0.6 | GL102: =1-CX102 -> 0.6 | ... JO102: =1-GA102 -> 1
B103: 40575 | C103: =D9 -> 26 | D103: =E9 -> 8 | E103: =F9 -> 8 | F103: =G9 -> 5 | G103: =H9 -> 5 | H103: =I9 -> 6 | I103: =J9 -> 2 | J103: =K9 -> 2 | ... CL103: =CM9 -> 0 | CP103: 40575 | CQ103: =C103/$C103 -> 1 | CR103: =D103/$C103 -> 0.30769231 | CS103: =E103/$C103 -> 0.30769231 | CT103: =F103/$C103 -> 0.19230769 | CU103: =G103/$C103 -> 0.19230769 | CV103: =H103/$C103 -> 0.23076923 | CW103: =I103/$C103 -> 0.076923077 | CX103: =J103/$C103 -> 0.076923077 | ... FZ103: =CL103/$C103 -> 0 | GD103: 40575 | GE103: =1-CQ103 -> 0 | GF103: =1-CR103 -> 0.69230769 | GG103: =1-CS103 -> 0.69230769 | GH103: =1-CT103 -> 0.80769231 | GI103: =1-CU103 -> 0.80769231 | GJ103: =1-CV103 -> 0.76923077 | GK103: =1-CW103 -> 0.92307692 | GL103: =1-CX103 -> 0.92307692 | ... JN103: =1-FZ103 -> 1
B104: 40603 | C104: =E10 -> 27 | D104: =F10 -> 8 | E104: =G10 -> 9 | F104: =H10 -> 7 | G104: =I10 -> 6 | H104: =J10 -> 5 | I104: =K10 -> 5 | J104: =L10 -> 6 | ... CK104: =CM10 -> 0 | CP104: 40603 | CQ104: =C104/$C104 -> 1 | CR104: =D104/$C104 -> 0.2962963 | CS104: =E104/$C104 -> 0.33333333 | CT104: =F104/$C104 -> 0.25925926 | CU104: =G104/$C104 -> 0.22222222 | CV104: =H104/$C104 -> 0.18518519 | CW104: =I104/$C104 -> 0.18518519 | CX104: =J104/$C104 -> 0.22222222 | ... FY104: =CK104/$C104 -> 0 | GD104: 40603 | GE104: =1-CQ104 -> 0 | GF104: =1-CR104 -> 0.7037037 | GG104: =1-CS104 -> 0.66666667 | GH104: =1-CT104 -> 0.74074074 | GI104: =1-CU104 -> 0.77777778 | GJ104: =1-CV104 -> 0.81481481 | GK104: =1-CW104 -> 0.81481481 | GL104: =1-CX104 -> 0.77777778 | ... JM104: =1-FY104 -> 1
B105: 40634 | C105: =F11 -> 19 | D105: =G11 -> 5 | E105: =H11 -> 4 | F105: =I11 -> 1 | G105: =J11 -> 1 | H105: =K11 -> 4 | I105: =L11 -> 0 | J105: =M11 -> 2 | ... CJ105: =CM11 -> 0 | CP105: 40634 | CQ105: =C105/$C105 -> 1 | CR105: =D105/$C105 -> 0.26315789 | CS105: =E105/$C105 -> 0.21052632 | CT105: =F105/$C105 -> 0.052631579 | CU105: =G105/$C105 -> 0.052631579 | CV105: =H105/$C105 -> 0.21052632 | CW105: =I105/$C105 -> 0 | CX105: =J105/$C105 -> 0.10526316 | ... FX105: =CJ105/$C105 -> 0 | GD105: 40634 | GE105: =1-CQ105 -> 0 | GF105: =1-CR105 -> 0.73684211 | GG105: =1-CS105 -> 0.78947368 | GH105: =1-CT105 -> 0.94736842 | GI105: =1-CU105 -> 0.94736842 | GJ105: =1-CV105 -> 0.78947368 | GK105: =1-CW105 -> 1 | GL105: =1-CX105 -> 0.89473684 | ... JL105: =1-FX105 -> 1
...
